Workbook

Sheet Stakeholder notes
A1: note_id | B1: stakeholder_name | C1: stakeholder_role | D1: quote_or_observation | E1: Assigned Theme
A2: SN-001 | B2: Amina Rahman | C2: Compliance Liaison | D2: Customers respond well when they have control and transparency about what they owe. | E2: Customer friction
A3: SN-002 | B3: Daniel Okoye | C3: Finance Business Partner | D3: Customers call back three times because they do not remember what they were told on the first call. | E3: Customer friction
A4: SN-003 | B4: Priya Nair | C4: Operations Manager | D4: Simple cases that could be resolved in minutes take days because they get stuck in the wrong queue. | E4: Delayed or missed follow-up
A5: SN-004 | B5: Gareth Evans | C5: Senior Collections Team Leader | D5: Leadership approved the roadmap five years ago and never came back to debt recovery. | E5: Change resistance or distrust
A6: SN-005 | B6: Tracy Field | C6: Systems Administrator | D6: Some customers will do anything if given the chance to manage this themselves. | E6: Customer friction
A7: SN-006 | B7: Sylvia Turner | C7: Operations Analyst | D7: We have no way to tell whether a customer is genuinely unable to pay or simply avoiding contact. | E7: Poor account-status visibility
A8: SN-007 | B8: Lawrence Bennett | C8: Finance Analyst | D8: We have cases sitting in 'awaiting callback' status for months because the promised date was never recorded. | E8: Delayed or missed follow-up
A9: SN-008 | B9: Andrea Hunt | C9: Operations Manager | D9: The audit trail is scattered across email, spreadsheets, and the legacy database, making compliance reviews a nightmare. | E9: Poor account-status visibility
A10: SN-009 | B10: Kimberley Richards-Stokes | C10: Service Design Lead | D10: Some customers will never use a portal no matter how good it is, and we need to plan for that. | E10: Customer friction
A11: SN-010 | B11: Mr Philip Stone | C11: Service Design Lead | D11: A single customer can have five separate records in the system from different entry points. | E11: Duplicated work
A12: SN-011 | B12: Christopher Richards | C12: Collections Representative | D12: The collections database does not sync with the email tracker, so representatives often re-contact customers who were already promised callbacks. | E12: Duplicated work
... A15: SN-014 | B15: Stewart Howell | C15: Operations Analyst | D15: We cannot tell whether a case failed because of process breakdown or deliberate non-compliance. | E15: Poor account-status visibility
A16: SN-015 | C16: Compliance Liaison | D16: A case marked 'resolved' in one system might be 'in progress' in another. | E16: Poor account-status visibility
A17: SN-016 | B17: Mr Dale Jackson | C17: Collections Representative | D17: The old system was designed for half the volume we handle now, and it shows. | E17: Change resistance or distrust
A18: SN-017 | B18: Eleanor Clark | C18: Service Design Lead | D18: Most customers do not even know they can pay online; they think they have to call. | E18: Customer friction
A19: SN-018 | B19: Daniel Farmer | C19: Finance Analyst | D19: Some representatives have been doing this for so long they are faster than the system, and they will resist change. | E19: Change resistance or distrust
A20: SN-019 | B20: Mr Martyn Akhtar | C20: Operations Analyst | D20: I cannot recommend automating anything until I see that it will not create new compliance risks. | E20: Change resistance or distrust
A21: SN-020 | B21: Ronald Rees | C21: Collections Representative | D21: New representatives take two weeks longer to reach productivity because they have to learn the spreadsheet system. | E21: Duplicated work
A22: SN-021 | B22: Clare Willis | C22: Service Design Lead | D22: With over 100,000 accounts, we cannot manage this manually any longer, yet that is exactly what we are doing. | E22: Change resistance or distrust
A23: SN-022 | B23: Rebecca Davis | C23: Compliance Liaison | D23: The database was designed for a tenth of the volume we handle now, and performance degrades as we approach month-end. | E23: Change resistance or distrust
A24: SN-023 | B24: Dr Louis Sinclair | C24: Service Design Lead | D24: We have more accounts in the system than our representatives can possibly contact in a reasonable timeframe. | E24: Delayed or missed follow-up
A25: SN-024 | B25: Dr Laura Roberts | C25: Compliance Liaison | D25: The scale of the problem means that even small improvements in efficiency multiply significantly. | E25: Change resistance or distrust
A26: SN-025 | B26: Dr Lynda Smith | C26: Operations Analyst | D26: The spreadsheet is now two hundred sheets thick and no one knows what half of them do. | E26: Duplicated work
A27: SN-026 | B27: Katherine Taylor-Evans | C27: Finance Analyst | D27: We have never measured how often a case comes back because we have no way to track it. | E27: Poor account-status visibility
A28: SN-027 | B28: Karl Lewis-Warren | C28: Operations Analyst | D28: Representatives spend time proving what they did rather than doing more work. | E28: Duplicated work
... A33: SN-032 | B33: Daniel Farmer | C33: Finance Analyst | D33: We lose customers because the recovery process is so slow they lose faith we will ever resolve it. | E33: Delayed or missed follow-up
A34: SN-033 | C34: Compliance Liaison | D34: We could recover an extra 5% of balances if we just contacted people at the right time. | E34: Delayed or missed follow-up
A35: SN-034 | B35: Lawrence Bennett | C35: Collections Representative | D35: Representatives are ready for better tools; they are tired of workarounds. | E35: Change resistance or distrust
A36: SN-035 | C36: Systems Administrator | D36: The database cannot handle the complexity of modern lending products and customer situations. | E36: Change resistance or distrust
A37: SN-036 | B37: Robert Quinn | C37: Process Improvement Lead | D37: Customers get transferred between departments and have to repeat their entire situation each time. | E37: Customer friction
A38: SN-037 | B38: Gareth Evans | C38: Operations Analyst | D38: The first contact with a customer is often not optimised because we do not know their full history. | E38: Poor account-status visibility
A39: SN-038 | B39: Sylvia Turner | C39: Operations Analyst | D39: The biggest win will be when representatives stop checking whether work was already done. | E39: Duplicated work
A40: SN-039 | B40: Simon Burns | C40: Compliance Liaison | D40: We do not have a way to identify which cases are straightforward versus which require specialist handling. | E40: Poor account-status visibility
A41: SN-040 | B41: Catherine Frost | C41: Data Analyst | D41: We lose at least 20% of follow-ups because they fall between shifts and no one owns the handoff. | E41: Delayed or missed follow-up
A42: SN-041 | B42: Peter Chambers | C42: Customer Service Lead | D42: We cannot automate the decision about whether a customer is genuinely in hardship or just dodging contact. | E42: Change resistance or distrust
A43: SN-042 | B43: Jennifer Hayes | C43: Systems Administrator | D43: We cannot tell whether a case failed because the representative made a mistake or because the customer is genuinely unable to pay. | E43: Poor account-status visibility
A44: SN-043 | B44: Simon Burns | C44: Compliance Liaison | D44: We need to measure whether this is better before we commit to rolling it out. | E44: Change resistance or distrust
A45: SN-044 | B45: Robert Quinn | C45: Process Improvement Lead | D45: If a customer pays even a small amount, the whole case gets reclassified and we lose months of history. | E45: Poor account-status visibility
A46: SN-045 | B46: Amina Rahman | C46: Head of Debt Recovery Operations | D46: The contact strategy is reactive—we contact people only when collections escalates them. | E46: Delayed or missed follow-up
A47: SN-046 | B47: Christopher Richards | C47: Collections Representative | D47: No one can tell me how much the current workarounds are costing us because the cost is hidden. | E47: Lack of confidence in the numbers
A48: SN-047 | B48: Diana White | C48: Collections Representative | D48: We are exposed to complaint risk because customers cannot track what we have told them. | E48: Customer friction
... A60: SN-059 | B60: James Morrison | C60: Quality Assurance Lead | D60: Representatives see solutions that the system does not allow them to implement. | E60: Change resistance or distrust
A61: SN-060 | C61: Collections Representative | D61: The compliance team says they cannot approve anything until they see the future process mapped out. | E61: Change resistance or distrust
A62: SN-061 | B62: Tracy Field | C62: Compliance Liaison | D62: The 20-year-old system was built for a different business model entirely. | E62: Change resistance or distrust
A63: SN-062 | B63: Simon Burns | C63: Compliance Liaison | D63: Every new tool we add makes the job harder because it adds another place where data can get out of sync. | E63: Duplicated work
A64: SN-063 | B64: Mr Martyn Akhtar | C64: Operations Analyst | D64: I cannot tell which customers have already been contacted this month without manually checking three different sheets. | E64: Duplicated work
A65: SN-064 | B65: Simon Burns | C65: Compliance Liaison | D65: The details matter more than the vision here. | E65: Change resistance or distrust
A66: SN-065 | B66: Dr Lynda Smith | C66: Operations Analyst | D66: Customers would pay more readily if they understood exactly what they owe and could see options. | E66: Customer friction
A67: SN-066 | B67: Jacqueline Norris | C67: Operations Analyst | D67: Audit trails across multiple systems make it nearly impossible to demonstrate what happened to a case. | E67: Poor account-status visibility
A68: SN-067 | B68: Dr Laura Roberts | C68: Compliance Liaison | D68: We are losing money on cases that fall through the cracks between systems. | E68: Delayed or missed follow-up
A69: SN-068 | B69: Dr Laura Roberts | C69: Compliance Liaison | D69: We lose good people because they get frustrated managing around the system instead of managing cases. | E69: Change resistance or distrust
A70: SN-069 | B70: Stewart Howell | D70: Cases involving vulnerable customers are not flagged differently from routine cases. | E70: Poor account-status visibility
A71: SN-070 | B71: Daniel Farmer | C71: Finance Analyst | D71: The finance team cannot forecast recovery revenue because they do not trust the activity data. | E71: Lack of confidence in the numbers
A72: SN-071 | B72: Tracy Field | D72: The finance team will ask for proof that this is not just shifting cost from operations to lost recovery. | E72: Lack of confidence in the numbers
A73: SN-072 | B73: Christopher Richards | C73: Collections Representative | D73: Experienced representatives are faster because they have memorised workarounds that should not be necessary. | E73: Change resistance or distrust
A74: SN-073 | B74: Mr Dale Jackson | C74: Collections Representative | D74: The activity log does not distinguish between actual contact and failed contact attempts. | E74: Poor account-status visibility
A75: SN-074 | B75: Jacqueline Norris | C75: Operations Analyst | D75: If we do not invest in this, we will keep losing good representatives to frustration. | E75: Change resistance or distrust
A76: SN-075 | B76: Daniel Farmer | C76: Finance Analyst | D76: Cases pile up on Fridays because no one wants to open new ones before the weekend. | E76: Delayed or missed follow-up
A77: SN-076 | B77: Peter Chambers | C77: Customer Service Lead | D77: The value case needs to account for the fact that some recoveries will take longer with self-service. | E77: Lack of confidence in the numbers
A78: SN-077 | B78: Clare Willis | C78: Service Design Lead | D78: We reach out to customers in a random order rather than any strategic sequence. | E78: Delayed or missed follow-up
A79: SN-078 | B79: Priya Nair | C79: Product Manager | D79: We reach out to customers in a random order rather than any strategic sequence. | E79: Delayed or missed follow-up
A80: SN-079 | B80: Gareth Evans | C80: Senior Collections Team Leader | D80: We do not have a way to identify which cases are straightforward versus which require specialist handling. | E80: Poor account-status visibility
A81: SN-080 | B81: Katherine Taylor-Evans | C81: Finance Analyst | D81: No one has visibility of what is actually in the pipeline or how long cases typically take. | E81: Poor account-status visibility
A82: SN-081 | B82: Tracy Field | C82: Compliance Liaison | D82: If the portal works, it will work because it gives customers control, not because it is fancier. | E82: Customer friction
A83: SN-082 | B83: Sarah Mitchell | C83: Collections Representative | D83: Self-service works well for straightforward cases, but we need to be honest about which ones those are. | E83: Change resistance or distrust
A84: SN-083 | B84: Clare Willis | C84: Service Design Lead | D84: Success looks different depending on who you ask. | E84: Change resistance or distrust
... A88: SN-087 | B88: Mr Dale Jackson | C88: Collections Representative | D88: We are paying representatives to hunt for information that should already be on the screen. | E88: Duplicated work
A89: SN-088 | B89: Peter Chambers | D89: We have no visibility into why cases are failing; we only know that they do. | E89: Poor account-status visibility
A90: SN-089 | B90: Eleanor Clark | C90: Service Design Lead | D90: We are treating this as a technology problem when some of it is a process problem. | E90: Change resistance or distrust
A91: SN-090 | B91: Robert Quinn | C91: Process Improvement Lead | D91: Some teams will embrace it immediately and others will resist until forced. | E91: Change resistance or distrust
A92: SN-091 | B92: Robert Quinn | C92: Process Improvement Lead | D92: Experienced representatives are faster because they have memorised workarounds that should not be necessary. | E92: Change resistance or distrust
A93: SN-092 | B93: Dr Laura Roberts | C93: Compliance Liaison | D93: The best representatives are being held back by process rather than enabled by it. | E93: Change resistance or distrust
A94: SN-093 | B94: Kimberley Richards-Stokes | C94: Compliance Liaison | D94: The 20-year-old system was built for a different business model entirely. | E94: Change resistance or distrust
A95: SN-094 | B95: Thomas Wright | C95: Operations Manager | D95: I spend more time reading notes from other representatives than I spend actually calling customers. | E95: Duplicated work
A96: SN-095 | B96: Priya Nair | C96: Product Manager | D96: Managers need a clear view of whether self-service actually reduces workload. | E96: Lack of confidence in the numbers
A97: SN-096 | B97: Mr Philip Stone | C97: Service Design Lead | D97: The spreadsheet workaround cost us five hundred thousand pounds in lost recovery last year. | E97: Lack of confidence in the numbers
A98: SN-097 | B98: Christopher Richards-Smith | C98: Collections Representative | D98: Representatives are afraid of the portal because they think it will take away their job, not because it won't work. | E98: Change resistance or distrust
A99: SN-098 | B99: Diana White | C99: Collections Representative | D99: I can see that work is happening, but I cannot see whether it is the right work. | E99: Poor account-status visibility
A100: SN-099 | B100: Tracy Field | C100: Compliance Liaison | D100: The portal could work brilliantly for the 40% of customers who want to resolve this themselves. | E100: Customer friction
A101: SN-100 | B101: Dr Lynda Smith | C101: Operations Analyst | D101: We are treating urgent cases and routine cases the same way, which is why everything feels urgent. | E101: Delayed or missed follow-up
... A127: SN-126 | B127: Christopher Richards | C127: Collections Representative | D127: The current system treats payment promises the same as payment confirmations, which creates confusion. | E127: Poor account-status visibility

Sheet Delinquent accounts
A1: account_id | B1: customer_id | C1: customer_name | D1: product_type | E1: delinquency_stage | F1: days_past_due | G1: overdue_amount | H1: total_balance | I1: risk_flag | J1: current_status | K1: email | L1: mobile_phone | M1: postcode | N1: last_contact_channel | O1: self_service_candidate | P1: created_date
A2: ACC-10001 | B2: CUST-50001 | C2: Naomi Clarke | D2: credit_card | E2: early | F2: 28 | G2: 1747.22 | H2: 14822.54 | I2: N | J2: plan_requested | K2: samuel11@example.net | L2: 42570632673 | M2: DD6H 8ZY | N2: letter | O2: Y | P2: 45993
A3: ACC-10002 | B3: CUST-50002 | C3: Dr Cameron Osborne | D3: personal_loan | E3: late | F3: 71 | G3: 772.39 | H3: 11496.59 | I3: Y | J3: Awaiting Follow Up | K3: kathleenmann@example.net | L3: 25813515656 | M3: W3 3NH | N3: email | O3: N | P3: 46000
A4: ACC-10003 | B4: CUST-50003 | C4: Heather Chapman | D4: credit_card | E4: early | F4: 26 | G4: 448.04 | H4: 14187.91 | I4: N | J4: plan_requested | K4: kathleenmorton@example.net | L4: 13900506764 | M4: CW15 2GJ | N4: phone | O4: Y | P4: 45987
A5: ACC-10004 | B5: CUST-50004 | C5: Rachael Butler-Bryant | D5: credit_card | E5: mid | F5: 37 | G5: 582.96 | H5: 14010.54 | I5: N | J5: email_sent | L5: 45463827169 | M5: B5D 7FE | N5: phone | O5: Y | P5: 45936
A6: ACC-10005 | B6: CUST-50005 | C6: William Bryant-Webb | D6: credit_card | E6: mid | F6: 45 | G6: 1300.23 | H6: 8733 | I6: N | J6: legal_watch | K6: gerald93@example.org | L6: 52289753626 | M6: L3 8ZB | N6: email | O6: Y | P6: 45965
A7: ACC-10006 | B7: CUST-50006 | C7: Robin Morris | D7: auto_finance | E7: mid | F7: 35 | G7: 362.91 | H7: 1788.57 | I7: N | J7: new_delinquency | K7: saramason@example.com | L7: 81202044445 | M7: TF8Y 4WY | N7: letter | O7: Y | P7: 46007
A8: ACC-10007 | B8: CUST-50007 | C8: Dr Reece Rose | D8: personal_loan | E8: early | F8: 5 | G8: 597.43 | H8: 14015.12 | I8: N | J8: promise_due | K8: reedshannon@example.net | L8: 61726202463 | M8: G0E 2BQ | N8: sms | O8: Y | P8: 46020
A9: ACC-10008 | B9: CUST-50008 | C9: Dorothy Bell | D9: credit_card | E9: early | F9: 23 | G9: 661.54 | H9: 10639.95 | I9: N | J9: manual_follow_up | K9: longpaul@example.com | L9: 99176632489 | M9: BD0A 0LF | O9: Y | P9: 45936
A10: ACC-10009 | B10: CUST-50009 | C10: Dr Connor Thomas | D10: personal_loan | E10: early | F10: 7 | G10: 1503.9 | H10: 12681.76 | I10: N | J10: email_sent | K10: sinclairanne@example.com | M10: KY4P 3UH | N10: sms | O10: Y | P10: 46029
A11: ACC-10010 | B11: CUST-50010 | C11: Mr Alex Taylor | D11: credit_card | E11: early | F11: 15 | G11: 1228.13 | H11: 9184.91 | I11: N | J11: no_response_cycle | K11: alanperkins@example.org | L11: 2164226547 | M11: CO9N 5YB | O11: Y | P11: 46042
A12: ACC-10011 | B12: CUST-50011 | C12: Dr Kathleen Ward | D12: personal_loan | E12: mid | F12: 56 | G12: 386.4 | H12: 12257.55 | I12: N | J12: awaiting_follow_up | K12: jonescarolyn@example.com | L12: 96527796128 | M12: B1 8YZ | O12: Y | P12: 45951
A13: ACC-10012 | B13: CUST-50012 | C13: Donald Donnelly | D13: credit_card | E13: early | F13: 11 | G13: 682.65 | H13: 13621.16 | I13: N | J13: plan_requested | K13: gerardrowe@example.net | L13: 51084777687 | M13: CB0P 1DP | N13: sms | O13: Y | P13: 46006
A14: ACC-10013 | B14: CUST-50013 | C14: Mrs Shannon James | D14: credit_card | E14: mid | F14: 45 | G14: 729.81 | H14: 6839.45 | I14: N | J14: new_delinquency | K14: pcoates@example.org | L14: 88228671202 | M14: S1H 5SZ | N14: phone | O14: Y | P14: 45935
A15: ACC-10014 | B15: CUST-50014 | C15: Brett Singh | D15: personal_loan | E15: early | F15: 13 | G15: 1566.5 | H15: 7156.99 | I15: Y | J15: promise_due | K15: danielsrosemary@example.com | L15: 88404142953 | M15: W0D 4YQ | N15: phone | O15: N | P15: 46018
A16: ACC-10015 | B16: CUST-50015 | C16: Mr Bernard Smith | D16: credit_card | E16: late | F16: 62 | G16: 1501.59 | H16: 15228.98 | I16: Y | J16: specialist_review | K16: jlewis@example.net | L16: 32750935905 | M16: G6D 3FW | N16: letter | O16: N | P16: 46040
A17: ACC-10016 | B17: CUST-50016 | C17: Sarah Hall | D17: credit_card | E17: late | F17: 113 | G17: 1558.83 | H17: 2446.02 | I17: N | J17: email sent | K17: conor42@example.com | L17: 35249640795 | M17: E0H 8RB | N17: email | O17: N | P17: 46022
A18: ACC-10017 | B18: CUST-50017 | C18: Eric Barry | D18: credit_card | E18: early | F18: 13 | G18: 128.42 | H18: 5556.24 | I18: N | J18: plan_requested | K18: brian76@example.net | L18: 28973634006 | M18: CF49 3TP | N18: phone | O18: Y | P18: 45973
A19: ACC-10018 | B19: CUST-50018 | C19: Ben Lane | D19: credit_card | E19: early | F19: 7 | G19: 1301.41 | H19: 3982.73 | I19: N | J19: specialist_review | K19: kellygeraldine@example.net | L19: 33226247040 | M19: DH3 8PE | O19: Y | P19: 45985
A20: ACC-10019 | B20: CUST-50019 | C20: Emma Wyatt | D20: personal_loan | E20: early | F20: 28 | G20: 896.1 | H20: 9198.91 | I20: N | J20: new_delinquency | K20: ehughes@example.com | L20: 56020223311 | M20: G3T 4FX | N20: email | O20: Y | P20: 45967
A21: ACC-10020 | B21: CUST-50020 | C21: Mrs Karen Brennan | D21: credit_card | E21: mid | F21: 58 | G21: 642.15 | H21: 10061.96 | I21: N | J21: new_delinquency | K21: nknight@example.org | L21: 91684370335 | M21: IM31 8GQ | O21: Y | P21: 45988
A22: ACC-10021 | B22: CUST-50021 | C22: Mark Wood-Smith | D22: personal_loan | E22: early | F22: 8 | G22: 900.88 | H22: 10538.77 | I22: Y | J22: specialist_review | K22: damian46@example.com | L22: 40391581782 | M22: TF44 3QF | N22: email | O22: N | P22: 46001
A23: ACC-10022 | B23: CUST-50022 | C23: Mr Jay Ferguson | D23: personal_loan | E23: early | F23: 17 | G23: 1275.07 | H23: 3231.5 | I23: Y | J23: plan_requested | K23: barbararowley@example.org | L23: 82324755216 | M23: SE4M 4UQ | N23: sms | O23: N | P23: 45986
A24: ACC-10023 | B24: CUST-50023 | C24: Mrs Beverley Riley | D24: personal_loan | E24: mid | F24: 32 | G24: 1681.9 | H24: 8188.01 | I24: N | J24: email_sent | K24: kdavies@example.org | L24: 36702855659 | M24: B1T 2TJ | N24: sms | O24: Y | P24: 45953
A25: ACC-10024 | B25: CUST-50024 | C25: Marilyn Glover-Mills | D25: personal_loan | E25: early | F25: 27 | G25: 1212.68 | H25: 9017.01 | I25: Y | J25: new_delinquency | K25: isaunders@example.org | L25: 75176280069 | M25: N11 3NJ | N25: sms | O25: N | P25: 46039
A26: ACC-10025 | B26: CUST-50025 | C26: Adam Morris-Lewis | D26: credit_card | E26: mid | F26: 39 | G26: 453.28 | H26: 13320.62 | I26: N | J26: awaiting_follow_up | L26: 495219135 | M26: KY8 3BL | N26: letter | O26: Y | P26: 45981
A27: ACC-10026 | B27: CUST-50026 | C27: Yvonne Preston | D27: personal_loan | E27: mid | F27: 37 | G27: 1302.31 | H27: 3558.24 | I27: N | J27: legal_watch | K27: omorgan@example.org | L27: 72100319569 | M27: LD5 4RB | N27: email | O27: Y | P27: 46013
A28: ACC-10027 | B28: CUST-50027 | C28: Nathan Bird | D28: credit_card | E28: late | F28: 102 | G28: 1700.93 | H28: 10074.31 | I28: Y | K28: kevinwilliams@example.net | L28: 87505332565 | M28: M90 4QU | O28: N | P28: 46036
A29: ACC-10028 | B29: CUST-50028 | C29: Eric Fowler | D29: credit_card | E29: late | F29: 88 | G29: 981.66 | H29: 10743.17 | I29: Y | J29: specialist_review | K29: jonesemma@example.com | L29: 67568602498 | M29: JE82 2ZX | N29: email | O29: N | P29: 45981
A30: ACC-10029 | B30: CUST-50029 | C30: Hannah Metcalfe | D30: credit_card | E30: early | F30: 17 | G30: 729.89 | H30: 14193.89 | I30: N | J30: plan_requested | K30: abdul90@example.net | L30: 81647237630 | M30: B5 1BW | N30: phone | O30: Y | P30: 45958
A31: ACC-10030 | B31: CUST-50030 | C31: Anna Mason-West | D31: personal_loan | E31: late | F31: 87 | G31: 406.56 | H31: 14114.63 | I31: Y | J31: specialist_review | M31: DH12 7LP | N31: email | O31: N | P31: 45975
A32: ACC-10031 | B32: CUST-50031 | C32: Naomi Smith | D32: credit_card | E32: early | F32: 27 | G32: 650.63 | H32: 9941.88 | I32: N | J32: manual_follow_up | K32: juliapugh@example.org | L32: 24286143109 | M32: S9 4GW | N32: letter | O32: Y | P32: 45932
A33: ACC-10032 | B33: CUST-50032 | C33: Susan Hamilton | D33: personal_loan | E33: early | F33: 9 | G33: 1788.68 | H33: 12003.84 | I33: N | J33: promise_due | K33: jbailey@example.org | L33: 67681241773 | M33: S96 0ZX | N33: sms | O33: Y | P33: 46021
A34: ACC-10033 | B34: CUST-50033 | C34: Geoffrey Jones-Hughes | D34: credit_card | E34: early | F34: 6 | G34: 1568.75 | H34: 8767.18 | I34: N | J34: awaiting_follow_up | K34: marc98@example.com | L34: 37439812559 | M34: CT0 8XX | N34: email | O34: Y | P34: 46031
A35: ACC-10034 | B35: CUST-50034 | C35: Brian Gibson-Graham | D35: personal_loan | E35: mid | F35: 37 | G35: 643.34 | H35: 1776.37 | I35: N | J35: specialist_review | K35: ellie60@example.net | L35: 6955851059 | M35: CA0 2JZ | N35: sms | O35: Y | P35: 46043
A36: ACC-10035 | B36: CUST-50035 | C36: Kerry Smith | D36: personal_loan | E36: mid | F36: 40 | G36: 485.46 | H36: 10324.18 | I36: N | J36: specialist_review | L36: 68828841543 | M36: G3 0UA | N36: phone | O36: Y | P36: 45978
A37: ACC-10036 | B37: CUST-50036 | C37: Dr Stephen Ward | D37: auto_finance | E37: early | F37: 22 | G37: 1685.69 | H37: 12357.23 | I37: N | J37: new_delinquency | K37: joshua29@example.net | L37: 91473267182 | M37: B9 1SJ | N37: phone | O37: Y | P37: 46021
A38: ACC-10037 | B38: CUST-50037 | C38: Elliot Miah | D38: credit_card | E38: mid | F38: 43 | G38: 365.08 | H38: 4012.64 | I38: N | J38: manual_follow_up | K38: kelly50@example.com | L38: 16115256537 | M38: N27 7TQ | N38: phone | O38: Y | P38: 45979
A39: ACC-10038 | B39: CUST-50038 | C39: Julie Norris | D39: personal_loan | E39: mid | F39: 51 | G39: 541.82 | H39: 1330.69 | I39: N | J39: new_delinquency | K39: nwallace@example.net | L39: 95243079840 | M39: S01 4YF | N39: phone | O39: Y | P39: 46003
A40: ACC-10039 | B40: CUST-50039 | C40: Patricia Cartwright-Phillips | D40: personal_loan | E40: early | F40: 17 | G40: 1288.67 | H40: 2152.48 | I40: N | J40: plan_requested | K40: owenkathryn@example.org | L40: 60214936268 | M40: B0W 4TH | O40: Y | P40: 46025
A41: ACC-10040 | B41: CUST-50040 | C41: Debra Smith | D41: credit_card | E41: mid | F41: 53 | G41: 382.24 | H41: 4046.88 | I41: N | J41: plan_requested | L41: 80654880705 | M41: B6A 7RQ | N41: letter | O41: Y | P41: 46045
A42: ACC-10041 | B42: CUST-50041 | C42: Jay Henderson | D42: credit_card | E42: mid | F42: 46 | G42: 89.92 | H42: 5659.83 | I42: N | J42: Awaiting Follow Up | K42: joanford@example.net | L42: 6769683808 | M42: S0 7WA | O42: Y | P42: 46015
A43: ACC-10042 | B43: CUST-50042 | C43: Arthur West | D43: personal_loan | E43: early | F43: 14 | G43: 1305.13 | H43: 3041.8 | I43: N | J43: awaiting_follow_up | K43: gwright@example.org | M43: HP84 2HL | O43: Y | P43: 46024
A44: ACC-10043 | B44: CUST-50043 | C44: Declan Smith | D44: credit_card | E44: early | F44: 23 | G44: 1551.3 | H44: 6225.68 | I44: N | J44: legal_watch | K44: josephine96@example.com | L44: 18093215607 | M44: CT63 9UQ | N44: phone | O44: Y | P44: 46011
A45: ACC-10044 | B45: CUST-50044 | C45: Dr Tracey Williams | D45: credit_card | E45: late | F45: 114 | G45: 1074.33 | H45: 14625.72 | I45: N | J45: legal_watch | K45: grace34@example.org | L45: 46830872404 | M45: B4 1WD | N45: email | O45: N | P45: 46039
A46: ACC-10045 | B46: CUST-50045 | C46: Paige Macdonald | D46: personal_loan | E46: early | F46: 16 | G46: 80.08 | H46: 12692.74 | I46: N | J46: plan_requested | K46: deborah76@example.org | L46: 7560540155 | M46: BH9P 1QA | N46: phone | O46: Y | P46: 45986
A47: ACC-10046 | B47: CUST-50046 | C47: Dr Anne Khan | D47: personal_loan | E47: early | F47: 21 | G47: 717.89 | H47: 1895.46 | I47: N | J47: manual_follow_up | K47: twhitehead@example.com | L47: 91986365816 | M47: N57 8PX | N47: sms | O47: Y | P47: 46009
A48: ACC-10047 | B48: CUST-50047 | C48: Mr Declan Wright | D48: credit_card | E48: mid | F48: 41 | G48: 1589.54 | H48: 11130.09 | I48: N | J48: legal_watch | K48: pcraig@example.com | L48: 36091213086 | M48: JE5W 5AX | N48: letter | O48: Y | P48: 46040
A49: ACC-10048 | B49: CUST-50048 | C49: Liam Whittaker | D49: credit_card | E49: early | F49: 16 | G49: 977.04 | H49: 1903.12 | I49: N | J49: no_response_cycle | K49: davisondiane@example.com | L49: 87766186548 | M49: BB59 4AP | O49: Y | P49: 46039
A50: ACC-10049 | B50: CUST-50049 | C50: Brandon Murphy | D50: personal_loan | E50: early | F50: 29 | G50: 1592.15 | H50: 10220.19 | I50: N | J50: legal_watch | K50: tclarke@example.com | L50: 26312412896 | M50: LD8 3FH | N50: email | O50: Y | P50: 45994
A51: ACC-10050 | B51: CUST-50050 | C51: Ms Kim Patel | D51: credit_card | E51: early | F51: 25 | G51: 1696.94 | H51: 15468.6 | I51: Y | J51: legal_watch | K51: woodstracey@example.com | L51: 1692449665 | M51: M90 3FP | N51: letter | O51: N | P51: 46036
A52: ACC-10051 | B52: CUST-50051 | C52: Luke Jones-Little | D52: personal_loan | E52: mid | F52: 41 | G52: 254.2 | H52: 1623.95 | I52: N | J52: promise_due | K52: fgallagher@example.com | L52: 32152813624 | M52: SM38 3RJ | O52: Y | P52: 45990
A53: ACC-10052 | B53: CUST-50052 | C53: Kerry Williams | D53: personal_loan | E53: early | F53: 20 | G53: 312.65 | H53: 7420.39 | I53: N | J53: manual_follow_up | K53: jonesanna@example.com | L53: 83110863886 | M53: M7 3XY | N53: sms | O53: Y | P53: 45951
A54: ACC-10053 | B54: CUST-50053 | C54: James Roberts | D54: credit_card | E54: early | F54: 8 | G54: 1197.84 | H54: 13054.45 | I54: N | J54: Awaiting Follow Up | K54: gillianstevens@example.org | L54: 85705376237 | M54: JE96 6BA | N54: phone | O54: Y | P54: 45964
A55: ACC-10054 | B55: CUST-50054 | C55: Christopher Johnson | D55: credit_card | E55: late | F55: 100 | G55: 1373.16 | H55: 7322.25 | I55: Y | J55: manual_follow_up | K55: shawdenise@example.org | L55: 20440909144 | M55: W4A 9LN | N55: phone | O55: N | P55: 46042
A56: ACC-10055 | B56: CUST-50055 | C56: Cameron Phillips | D56: personal_loan | E56: early | F56: 13 | G56: 791.08 | H56: 7104.61 | I56: Y | J56: Awaiting Follow Up | K56: marcthomas@example.org | L56: 54472161279 | M56: KW6M 6JD | N56: email | O56: N | P56: 46006
A57: ACC-10056 | B57: CUST-50056 | C57: Miss Shannon Hunter | D57: personal_loan | E57: mid | F57: 36 | G57: 583.8 | H57: 13372.33 | I57: N | J57: no_response_cycle | K57: gilliandixon@example.com | L57: 29252799395 | M57: B13 0HG | N57: email | O57: Y | P57: 45931
A58: ACC-10057 | B58: CUST-50057 | C58: Stephen Ford | D58: personal_loan | E58: early | F58: 22 | G58: 1010.98 | H58: 10799.98 | I58: N | J58: plan_requested | K58: pelliott@example.org | L58: 19542556948 | M58: CT2P 6EH | N58: phone | O58: Y | P58: 45983
A59: ACC-10058 | B59: CUST-50058 | C59: Ms Carolyn Page | D59: personal_loan | E59: early | F59: 21 | G59: 277.17 | H59: 12006.66 | I59: N | J59: plan_requested | K59: terrylewis@example.org | L59: 62329379194 | M59: G6D 1GG | N59: letter | O59: Y | P59: 45952
A60: ACC-10059 | B60: CUST-50059 | C60: Deborah Mistry-Taylor | D60: credit_card | E60: early | F60: 13 | G60: 1797.49 | H60: 7919.63 | I60: N | J60: email_sent | K60: phillip23@example.net | L60: 35401267844 | M60: W87 3QQ | N60: sms | O60: Y | P60: 45943
A61: ACC-10060 | B61: CUST-50060 | C61: Deborah Barber | D61: credit_card | E61: mid | F61: 43 | G61: 320.17 | H61: 3842.44 | I61: N | J61: awaiting_follow_up | K61: callum36@example.net | L61: 73711007868 | M61: CT4 8SW | N61: phone | O61: Y | P61: 45975
A62: ACC-10061 | B62: CUST-50061 | C62: Sharon Palmer | D62: credit_card | E62: early | F62: 6 | G62: 1090.24 | H62: 9357.84 | I62: N | J62: promise_due | K62: jessica71@example.org | L62: 44036325004 | M62: S9G 5HQ | N62: email | O62: Y | P62: 45970
A63: ACC-10062 | B63: CUST-50062 | C63: Elliot Warren | D63: credit_card | E63: mid | F63: 33 | G63: 505.69 | H63: 8000.73 | I63: N | J63: new delinquency | K63: jtaylor@example.net | L63: 57179487001 | M63: N7U 9WT | N63: sms | O63: Y | P63: 45948
A64: ACC-10063 | B64: CUST-50063 | C64: Jonathan Fleming | D64: credit_card | E64: early | F64: 12 | G64: 779.84 | H64: 8300.45 | I64: N | J64: plan_requested | K64: osbornegemma@example.net | L64: 45085465230 | M64: G57 3LZ | N64: sms | O64: Y | P64: 45938
... A67: ACC-10066 | B67: CUST-50066 | C67: Mr Eric Edwards | D67: auto_finance | E67: early | F67: 27 | G67: 286.97 | H67: 12569.2 | I67: N | J67: email_sent | K67: leewendy@example.net | L67: 33751258732 | M67: G7 6AB | N67: sms | O67: Y | P67: 45960
A68: ACC-10067 | B68: CUST-50067 | C68: Sophie King | D68: personal_loan | E68: mid | F68: 57 | G68: 1434.26 | H68: 7808.55 | I68: N | J68: plan_requested | K68: andrewssuzanne@example.com | M68: G3 9PX | N68: phone | O68: Y | P68: 46000
A69: ACC-10068 | B69: CUST-50068 | C69: Douglas Wright | D69: credit_card | E69: early | F69: 13 | G69: 971.03 | H69: 1483.99 | I69: N | J69: awaiting_follow_up | K69: hughwalker@example.net | L69: 4765055892 | M69: S6 8QZ | N69: phone | O69: Y | P69: 46046
A70: ACC-10069 | B70: CUST-50069 | C70: Albert Smith | D70: auto_finance | E70: late | F70: 85 | G70: 1397.76 | H70: 6560.21 | I70: N | K70: milesamelia@example.org | L70: 48608433003 | M70: BR3Y 9JL | N70: letter | O70: N | P70: 46002
A71: ACC-10070 | B71: CUST-50070 | C71: Bryan Stevens-Smart | D71: credit_card | E71: early | F71: 29 | G71: 1681.54 | H71: 4657.78 | I71: N | K71: gordonharrison@example.com | L71: 64984495814 | M71: CW2 1DT | O71: Y | P71: 45983
A72: ACC-10071 | B72: CUST-50071 | C72: Janet Potter | D72: personal_loan | E72: late | F72: 108 | G72: 1696.78 | H72: 9182.98 | I72: Y | J72: email_sent | K72: uwilson@example.com | L72: 1012612062 | M72: KT42 1PG | N72: sms | O72: N | P72: 45983
A73: ACC-10072 | B73: CUST-50072 | C73: Joseph Gough | D73: credit_card | E73: mid | F73: 34 | G73: 1343.42 | H73: 13167.4 | I73: N | J73: email_sent | K73: jamesjulie@example.net | L73: 84632526696 | M73: PR0A 2HU | N73: phone | O73: Y | P73: 45944
A74: ACC-10073 | B74: CUST-50073 | C74: Hollie Owen | D74: personal_loan | E74: early | F74: 23 | G74: 1515.86 | H74: 3502.88 | I74: N | J74: legal_watch | K74: frederick66@example.net | L74: 83394411798 | M74: E0C 0LY | N74: letter | O74: Y | P74: 45960
A75: ACC-10074 | B75: CUST-50074 | C75: Jake Lewis-Akhtar | D75: credit_card | E75: late | F75: 106 | G75: 930.53 | H75: 6122.31 | I75: Y | J75: legal_watch | K75: wmoran@example.org | L75: 76354794570 | M75: W8T 6QW | N75: sms | O75: N | P75: 45979
A76: ACC-10075 | B76: CUST-50075 | C76: Paul Pritchard-Phillips | D76: personal_loan | E76: early | F76: 29 | G76: 1234.88 | H76: 4041.45 | I76: Y | J76: new_delinquency | K76: woodgerard@example.net | L76: 61907346604 | M76: DH0 3PU | N76: phone | O76: N | P76: 46024
A77: ACC-10076 | B77: CUST-50076 | C77: Terence Atkinson | D77: personal_loan | E77: late | F77: 84 | G77: 310.52 | H77: 5605.78 | I77: N | J77: specialist_review | K77: gjohnson@example.com | L77: 12741589075 | M77: E68 7YS | N77: phone | O77: N | P77: 45975
A78: ACC-10077 | B78: CUST-50077 | C78: Dr Louise Smith | D78: personal_loan | E78: early | F78: 26 | G78: 136.6 | H78: 2019.65 | I78: N | J78: plan_requested | K78: burkemathew@example.org | L78: 1865878461 | M78: S28 4XP | O78: Y | P78: 45984
A79: ACC-10078 | B79: CUST-50078 | C79: Russell Walker | D79: auto_finance | E79: early | F79: 25 | G79: 824.18 | H79: 3115.95 | I79: N | J79: legal_watch | K79: clarkdennis@example.net | L79: 11064206023 | M79: PO1 8EA | N79: phone | O79: Y | P79: 46016
A80: ACC-10079 | B80: CUST-50079 | C80: Mr Robert Davies | D80: personal_loan | E80: mid | F80: 42 | G80: 1033.7 | H80: 2841.57 | I80: N | J80: legal_watch | K80: paul61@example.org | L80: 75006781071 | M80: EC0 4XP | N80: sms | O80: Y | P80: 45999
A81: ACC-10080 | B81: CUST-50080 | C81: Douglas Rowe | D81: personal_loan | E81: mid | F81: 45 | G81: 1092.43 | H81: 5884.24 | I81: N | J81: Awaiting Follow Up | K81: qhancock@example.org | L81: 69943513049 | M81: IM9 4HZ | N81: email | O81: Y | P81: 45943
A82: ACC-10081 | B82: CUST-50081 | C82: Dr Stewart Clements | D82: credit_card | E82: early | F82: 17 | G82: 1246.33 | H82: 6377.85 | I82: N | J82: plan_requested | K82: patricia86@example.net | M82: NR8B 8JR | N82: letter | O82: N | P82: 45994
A83: ACC-10082 | B83: CUST-50082 | C83: Simon Jackson | D83: credit_card | E83: early | F83: 17 | G83: 952.49 | H83: 6581.32 | I83: N | J83: no_response_cycle | K83: wayne50@example.org | L83: 32751607381 | M83: M21 4WX | O83: Y | P83: 45956
A84: ACC-10083 | B84: CUST-50083 | C84: Sara Morris | D84: credit_card | E84: early | F84: 25 | G84: 977.15 | H84: 7433.91 | I84: N | J84: legal_watch | K84: liamthorpe@example.org | L84: 63722837738 | M84: N5 4GZ | N84: phone | O84: Y | P84: 45953
A85: ACC-10084 | B85: CUST-50084 | C85: Miss Amanda Wright | D85: personal_loan | E85: early | F85: 18 | G85: 983.77 | H85: 4367.42 | I85: N | J85: email_sent | K85: reeceflynn@example.org | L85: 13549862477 | M85: NG53 1FJ | N85: phone | O85: Y | P85: 46012
A86: ACC-10085 | B86: CUST-50085 | C86: Bryan Thomas | D86: credit_card | E86: early | F86: 17 | G86: 829.45 | H86: 3498.07 | I86: N | J86: Awaiting Follow Up | K86: rhaynes@example.com | L86: 6433583302 | M86: BB05 2HS | N86: phone | O86: Y | P86: 45996
A87: ACC-10086 | B87: CUST-50086 | C87: Lucy Phillips | D87: credit_card | E87: early | F87: 6 | G87: 452.89 | H87: 11536.12 | I87: N | J87: plan_requested | K87: bakerfiona@example.net | L87: 78029222697 | M87: PA6A 9SD | N87: letter | O87: Y | P87: 45982
A88: ACC-10087 | B88: CUST-50087 | C88: Melissa Ball | D88: personal_loan | E88: early | F88: 8 | G88: 656.19 | H88: 13353.37 | I88: N | J88: specialist_review | K88: dalesaunders@example.org | L88: 27765064219 | M88: AL4 2EW | N88: email | O88: Y | P88: 46002
A89: ACC-10088 | B89: CUST-50088 | C89: Bradley Hall | D89: credit_card | E89: early | F89: 12 | G89: 1747.53 | H89: 8133.99 | I89: N | J89: legal_watch | K89: wayne47@example.org | L89: 12106648352 | M89: DL41 3LP | N89: phone | O89: Y | P89: 46024
A90: ACC-10089 | B90: CUST-50089 | C90: Katie Pearson | D90: personal_loan | E90: mid | F90: 30 | G90: 751.65 | H90: 4251.41 | I90: N | J90: no_response_cycle | K90: wallallan@example.net | L90: 49374641678 | M90: N9D 2WL | N90: sms | O90: Y | P90: 45992
A91: ACC-10090 | B91: CUST-50090 | C91: Roy Marshall-Newman | D91: personal_loan | E91: early | F91: 12 | G91: 1608.3 | H91: 14626.42 | I91: Y | J91: manual_follow_up | K91: linda51@example.org | L91: 60987687468 | M91: B0 4WR | N91: letter | O91: N | P91: 45938
A92: ACC-10091 | B92: CUST-50091 | C92: Maria Harding-Reid | D92: auto_finance | E92: early | F92: 29 | G92: 769.35 | H92: 3840.45 | I92: N | J92: specialist_review | K92: jodierees@example.net | L92: 51111678803 | M92: W3S 7TL | N92: phone | O92: Y | P92: 45932
A93: ACC-10092 | B93: CUST-50092 | C93: Caroline Yates-Harrison | D93: personal_loan | E93: mid | F93: 58 | G93: 329.89 | H93: 9113.04 | I93: N | J93: manual_follow_up | L93: 21450267747 | M93: M2B 6DH | O93: Y | P93: 45940
A94: ACC-10093 | B94: CUST-50093 | C94: Mr Brandon Begum | D94: auto_finance | E94: mid | F94: 55 | G94: 973.08 | H94: 8143.6 | I94: Y | J94: Awaiting Follow Up | K94: mgriffiths@example.com | L94: 82400707833 | M94: WN8 8EU | N94: email | O94: N | P94: 45956
A95: ACC-10094 | B95: CUST-50094 | C95: Julie Harris-Ashton | D95: credit_card | E95: early | F95: 15 | G95: 586.35 | H95: 7387.8 | I95: N | J95: specialist_review | K95: zporter@example.com | L95: 1449885175 | M95: L1 0YG | N95: letter | O95: Y | P95: 45980
A96: ACC-10095 | B96: CUST-50095 | C96: Mr Jonathan Hilton | D96: credit_card | E96: mid | F96: 37 | G96: 210.77 | H96: 10950.45 | I96: N | J96: specialist_review | K96: hollie59@example.org | L96: 44611774738 | M96: PE7 4PU | N96: email | O96: Y | P96: 46047
A97: ACC-10096 | B97: CUST-50096 | C97: Samuel Allen | D97: credit_card | E97: early | F97: 10 | G97: 1150.24 | H97: 13375.47 | I97: N | J97: plan_requested | K97: ricedarren@example.org | L97: 79433093290 | M97: L94 2XJ | N97: email | O97: Y | P97: 46050
A98: ACC-10097 | B98: CUST-50097 | C98: Ms Carol Smith | D98: credit_card | E98: early | F98: 5 | G98: 1306.75 | H98: 11627.93 | I98: N | J98: manual_follow_up | K98: christopherbutler@example.org | L98: 37988279548 | M98: N2H 7JP | N98: email | O98: Y | P98: 45978
A99: ACC-10098 | B99: CUST-50098 | C99: Josephine Burton-Atkinson | D99: credit_card | E99: early | F99: 23 | G99: 1430.77 | H99: 11192.75 | I99: N | J99: legal_watch | K99: sallysutton@example.com | L99: 31757358685 | M99: PR7 8EX | N99: phone | O99: Y | P99: 45958
A100: ACC-10099 | B100: CUST-50099 | C100: Bradley Griffin | D100: credit_card | E100: mid | F100: 37 | G100: 1317.86 | H100: 8706.41 | I100: N | J100: specialist_review | K100: dorothywillis@example.net | L100: 34129341963 | M100: KY9 3DS | O100: Y | P100: 45969
A101: ACC-10100 | B101: CUST-50100 | C101: Gerard Johnson-King | D101: credit_card | E101: early | F101: 9 | G101: 479 | H101: 2433.81 | I101: N | J101: manual_follow_up | K101: bdavies@example.net | L101: 53355916358 | M101: SG4 5SD | N101: email | O101: Y | P101: 45959
A102: ACC-10101 | B102: CUST-50101 | C102: Dr Ryan Miller | D102: credit_card | E102: early | F102: 8 | G102: 1426.86 | H102: 7003.13 | I102: N | J102: new_delinquency | L102: 49862436415 | M102: DN28 4UP | N102: email | O102: Y | P102: 45940
...

Sheet Recovery activity tracker
A1: activity_id | B1: account_id | C1: activity_date | D1: activity_type | E1: performed_by | F1: source_system | G1: outcome_code | H1: next_follow_up_date | I1: minutes_spent | J1: duplicate_check_flag
A2: ACT-00001 | B2: ACC-10001 | C2: 46056 | D2: status_check | E2: representative_38 | F2: spreadsheet | G2: next_action_unclear | I2: 3 | J2: N
A3: ACT-00002 | B3: ACC-10001 | C3: 46041 | D3: manual_plan_note | E3: representative_48 | F3: phone | G3: viewed_status | H3: 46046 | I3: 8 | J3: N
A4: ACT-00003 | B4: ACC-10001 | C4: 46049 | D4: status_check | E4: representative_32 | F4: phone | G4: promise_to_pay | H4: 46056 | I4: 4 | J4: Y
A5: ACT-00004 | B5: ACC-10001 | C5: 46061 | D5: email_sent | E5: representative_08 | F5: phone | G5: no_reply | H5: 46066 | I5: 4 | J5: N
A6: ACT-00005 | B6: ACC-10001 | C6: 46059 | D6: escalation | E6: representative_28 | F6: spreadsheet | G6: next_action_unclear | I6: 8 | J6: N
A7: ACT-00006 | B7: ACC-10002 | C7: 46027 | D7: call_attempt | E7: representative_05 | F7: phone | G7: promise_to_pay | H7: 46028 | I7: 11 | J7: N
A8: ACT-00007 | B8: ACC-10002 | C8: 46034 | D8: spreadsheet_reconcile | E8: representative_04 | F8: legacy_db | G8: next_action_unclear | H8: 46034 | I8: 9 | J8: Y
A9: ACT-00008 | B9: ACC-10002 | C9: 46039 | D9: email_sent | E9: representative_25 | F9: phone | G9: awaiting_review | H9: 46045 | I9: 5 | J9: N
A10: ACT-00009 | B10: ACC-10002 | C10: 46025 | D10: escalation | E10: representative_04 | F10: legacy_db | G10: updated_row | H10: 46025 | I10: 6 | J10: N
A11: ACT-00010 | B11: ACC-10002 | C11: 46028 | D11: manual_plan_note | E11: representative_49 | F11: phone | G11: awaiting_review | H11: 46031 | I11: 10 | J11: N
A12: ACT-00011 | B12: ACC-10003 | C12: 46068 | D12: manual_plan_note | E12: representative_09 | F12: phone | G12: left_message | I12: 10 | J12: N
A13: ACT-00012 | B13: ACC-10003 | C13: 46066 | D13: email_sent | E13: representative_48 | F13: legacy_db | G13: no_reply | H13: 46072 | I13: 4 | J13: N
A14: ACT-00013 | B14: ACC-10003 | C14: 46062 | D14: spreadsheet_reconcile | E14: representative_49 | F14: email | G14: sent_to_specialist | H14: 46063 | I14: 12 | J14: N
A15: ACT-00014 | B15: ACC-10003 | C15: 46061 | D15: status_check | E15: representative_06 | F15: spreadsheet | G15: next_action_unclear | H15: 46063 | I15: 5 | J15: Y
A16: ACT-00015 | B16: ACC-10003 | C16: 46076 | D16: status_check | E16: representative_48 | F16: email | G16: awaiting_review | H16: 46083 | I16: 3 | J16: Y
A17: ACT-00016 | B17: ACC-10004 | C17: 46066 | D17: spreadsheet_reconcile | E17: representative_36 | F17: phone | G17: updated_row | H17: 46072 | I17: 10 | J17: N
A18: ACT-00017 | B18: ACC-10004 | C18: 46068 | D18: call_attempt | E18: representative_33 | F18: spreadsheet | G18: sent_to_specialist | H18: 46068 | I18: 11 | J18: N
A19: ACT-00018 | B19: ACC-10005 | C19: 46049 | D19: email_sent | E19: representative_49 | F19: phone | G19: updated_row | I19: 4 | J19: N
A20: ACT-00019 | B20: ACC-10006 | C20: 46052 | D20: call_attempt | E20: representative_30 | F20: phone | G20: no_reply | I20: 12 | J20: N
A21: ACT-00020 | B21: ACC-10007 | C21: 46044 | D21: call_attempt | E21: representative_27 | F21: legacy_db | G21: next_action_unclear | H21: 46049 | I21: 11 | J21: N
A22: ACT-00021 | B22: ACC-10007 | C22: 46046 | D22: status_check | E22: representative_07 | F22: phone | G22: left_message | H22: 46048 | I22: 4 | J22: Y
A23: ACT-00022 | B23: ACC-10007 | C23: 46046 | D23: call_attempt | E23: representative_35 | F23: phone | G23: sent_to_specialist | H23: 46051 | I23: 9 | J23: N
A24: ACT-00023 | B24: ACC-10008 | C24: 46066 | D24: email_sent | E24: representative_35 | F24: phone | G24: awaiting_review | H24: 46066 | I24: 7 | J24: N
A25: ACT-00024 | B25: ACC-10008 | C25: 46054 | D25: manual_plan_note | E25: representative_07 | F25: legacy_db | G25: updated_row | H25: 46056 | I25: 5 | J25: N
A26: ACT-00025 | B26: ACC-10009 | C26: 46062 | D26: spreadsheet_reconcile | E26: representative_34 | F26: email | G26: updated_row | H26: 46066 | I26: 9 | J26: Y
A27: ACT-00026 | B27: ACC-10009 | C27: 46058 | D27: call_attempt | E27: representative_22 | F27: legacy_db | G27: no_reply | H27: 46064 | I27: 14 | J27: N
A28: ACT-00027 | B28: ACC-10009 | C28: 46076 | D28: sms_reminder | E28: representative_09 | F28: spreadsheet | G28: left_message | H28: 46079 | I28: 4 | J28: N
A29: ACT-00028 | B29: ACC-10010 | C29: 46051 | D29: escalation | E29: representative_01 | F29: phone | G29: sent_to_specialist | H29: 46052 | I29: 11 | J29: N
A30: ACT-00029 | B30: ACC-10010 | C30: 46039 | D30: spreadsheet_reconcile | E30: representative_40 | F30: legacy_db | G30: updated_row | H30: 46039 | I30: 10 | J30: Y
A31: ACT-00030 | B31: ACC-10010 | C31: 46046 | D31: call_attempt | E31: representative_51 | F31: spreadsheet | G31: awaiting_review | H31: 46048 | I31: 14 | J31: N
A32: ACT-00031 | B32: ACC-10010 | C32: 46047 | D32: sms_reminder | E32: representative_53 | F32: spreadsheet | G32: next_action_unclear | I32: 3 | J32: N
A33: ACT-00032 | B33: ACC-10010 | C33: 46054 | D33: email_sent | E33: representative_48 | F33: legacy_db | G33: updated_row | H33: 46056 | I33: 4 | J33: N
A34: ACT-00033 | B34: ACC-10011 | C34: 46081 | D34: escalation | E34: representative_16 | F34: spreadsheet | G34: awaiting_review | H34: 46086 | I34: 10 | J34: N
A35: ACT-00034 | B35: ACC-10011 | C35: 46064 | D35: spreadsheet_reconcile | E35: representative_43 | F35: phone | G35: left_message | H35: 46067 | I35: 9 | J35: N
A36: ACT-00035 | B36: ACC-10011 | C36: 46068 | D36: call_attempt | E36: representative_43 | F36: legacy_db | G36: viewed_status | H36: 46068 | I36: 13 | J36: N
A37: ACT-00036 | B37: ACC-10012 | C37: 46074 | D37: email_sent | E37: representative_34 | F37: legacy_db | G37: sent_to_specialist | H37: 46076 | I37: 5 | J37: N
A38: ACT-00037 | B38: ACC-10012 | C38: 46072 | D38: call_attempt | E38: representative_28 | F38: spreadsheet | G38: next_action_unclear | H38: 46077 | I38: 11 | J38: N
A39: ACT-00038 | B39: ACC-10012 | C39: 46071 | D39: email_sent | E39: representative_42 | F39: spreadsheet | G39: viewed_status | H39: 46071 | I39: 5 | J39: N
A40: ACT-00039 | B40: ACC-10012 | C40: 46075 | D40: sms_reminder | E40: representative_24 | F40: legacy_db | G40: updated_row | H40: 46079 | I40: 4 | J40: N
A41: ACT-00040 | B41: ACC-10012 | C41: 46083 | D41: spreadsheet_reconcile | E41: representative_50 | F41: legacy_db | G41: sent_to_specialist | I41: 12 | J41: Y
A42: ACT-00041 | B42: ACC-10013 | C42: 46067 | D42: manual_plan_note | E42: representative_39 | F42: email | G42: next_action_unclear | H42: 46073 | I42: 8 | J42: N
A43: ACT-00042 | B43: ACC-10014 | C43: 46043 | D43: status_check | E43: representative_01 | F43: email | G43: updated_row | H43: 46045 | I43: 3 | J43: Y
A44: ACT-00043 | B44: ACC-10014 | C44: 46028 | D44: email_sent | E44: representative_18 | F44: email | G44: awaiting_review | H44: 46031 | I44: 4 | J44: N
A45: ACT-00044 | B45: ACC-10015 | C45: 46027 | D45: escalation | E45: representative_34 | F45: legacy_db | G45: viewed_status | H45: 46029 | I45: 7 | J45: N
A46: ACT-00045 | B46: ACC-10015 | C46: 46040 | D46: sms_reminder | E46: representative_28 | F46: email | G46: sent_to_specialist | H46: 46044 | I46: 3 | J46: N
A47: ACT-00046 | B47: ACC-10016 | C47: 46056 | D47: status_check | E47: representative_19 | F47: phone | G47: next_action_unclear | H47: 46062 | I47: 6 | J47: Y
A48: ACT-00047 | B48: ACC-10016 | C48: 46047 | D48: sms_reminder | E48: representative_51 | F48: phone | G48: sent_to_specialist | H48: 46047 | I48: 2 | J48: N
A49: ACT-00048 | B49: ACC-10017 | C49: 46057 | D49: status_check | E49: representative_46 | F49: spreadsheet | G49: awaiting_review | H49: 46064 | I49: 5 | J49: Y
A50: ACT-00049 | B50: ACC-10017 | C50: 46049 | D50: manual_plan_note | E50: representative_21 | F50: spreadsheet | G50: awaiting_review | H50: 46053 | I50: 5 | J50: N
A51: ACT-00050 | B51: ACC-10017 | C51: 46058 | D51: spreadsheet_reconcile | E51: representative_04 | F51: legacy_db | G51: viewed_status | H51: 46059 | I51: 9 | J51: Y
A52: ACT-00051 | B52: ACC-10017 | C52: 46042 | D52: email_sent | E52: representative_30 | F52: email | G52: promise_to_pay | I52: 7 | J52: N
A53: ACT-00052 | B53: ACC-10018 | C53: 46056 | D53: manual_plan_note | E53: representative_04 | F53: legacy_db | G53: viewed_status | H53: 46060 | I53: 10 | J53: N
A54: ACT-00053 | B54: ACC-10019 | C54: 46037 | D54: status_check | E54: representative_53 | F54: legacy_db | G54: promise_to_pay | H54: 46042 | I54: 5 | J54: Y
A55: ACT-00054 | B55: ACC-10019 | C55: 46041 | D55: status_check | E55: representative_50 | F55: email | G55: next_action_unclear | H55: 46043 | I55: 5 | J55: Y
A56: ACT-00055 | B56: ACC-10020 | C56: 46064 | D56: sms_reminder | E56: representative_54 | F56: email | G56: no_reply | H56: 46064 | I56: 2 | J56: N
A57: ACT-00056 | B57: ACC-10021 | C57: 46078 | D57: manual_plan_note | E57: representative_22 | F57: phone | G57: viewed_status | H57: 46085 | I57: 5 | J57: N
A58: ACT-00057 | B58: ACC-10021 | C58: 46080 | D58: spreadsheet_reconcile | E58: representative_54 | F58: phone | G58: viewed_status | H58: 46080 | I58: 7 | J58: N
A59: ACT-00058 | B59: ACC-10022 | C59: 46058 | D59: manual_plan_note | E59: representative_42 | F59: legacy_db | G59: viewed_status | H59: 46064 | I59: 7 | J59: N
A60: ACT-00059 | B60: ACC-10022 | C60: 46053 | D60: email_sent | E60: representative_38 | F60: phone | G60: next_action_unclear | H60: 46060 | I60: 4 | J60: N
A61: ACT-00060 | B61: ACC-10022 | C61: 46065 | D61: spreadsheet_reconcile | E61: representative_07 | F61: legacy_db | G61: promise_to_pay | H61: 46071 | I61: 11 | J61: N
A62: ACT-00061 | B62: ACC-10023 | C62: 46070 | D62: call_attempt | E62: representative_15 | F62: spreadsheet | G62: viewed_status | H62: 46077 | I62: 8 | J62: N
A63: ACT-00062 | B63: ACC-10023 | C63: 46056 | D63: manual_plan_note | E63: representative_27 | F63: phone | G63: sent_to_specialist | I63: 8 | J63: N
A64: ACT-00063 | B64: ACC-10023 | C64: 46062 | D64: status_check | E64: representative_29 | F64: legacy_db | G64: awaiting_review | H64: 46069 | I64: 5 | J64: Y
A65: ACT-00064 | B65: ACC-10023 | C65: 46069 | D65: email_sent | E65: representative_21 | F65: phone | G65: left_message | H65: 46076 | I65: 4 | J65: N
A66: ACT-00065 | B66: ACC-10023 | C66: 46054 | D66: escalation | E66: representative_20 | F66: phone | G66: updated_row | H66: 46056 | I66: 7 | J66: N
A67: ACT-00066 | B67: ACC-10024 | C67: 46074 | D67: status_check | E67: representative_20 | F67: email | G67: sent_to_specialist | I67: 4 | J67: N
A68: ACT-00067 | B68: ACC-10024 | C68: 46080 | D68: manual_plan_note | E68: representative_04 | F68: email | G68: no_reply | H68: 46086 | I68: 8 | J68: N
A69: ACT-00068 | B69: ACC-10024 | C69: 46076 | D69: sms_reminder | E69: representative_20 | F69: spreadsheet | G69: viewed_status | H69: 46078 | I69: 4 | J69: N
A70: ACT-00069 | B70: ACC-10024 | C70: 46083 | D70: escalation | E70: representative_44 | F70: phone | G70: updated_row | I70: 8 | J70: N
A71: ACT-00070 | B71: ACC-10025 | C71: 46051 | D71: sms_reminder | E71: representative_53 | F71: spreadsheet | G71: awaiting_review | I71: 2 | J71: N
A72: ACT-00071 | B72: ACC-10025 | C72: 46037 | D72: manual_plan_note | E72: representative_31 | F72: legacy_db | G72: left_message | I72: 10 | J72: N
A73: ACT-00072 | B73: ACC-10025 | C73: 46034 | D73: call_attempt | E73: representative_46 | F73: email | G73: awaiting_review | H73: 46038 | I73: 13 | J73: N
A74: ACT-00073 | B74: ACC-10025 | C74: 46041 | D74: manual_plan_note | E74: representative_36 | F74: legacy_db | G74: left_message | H74: 46048 | I74: 7 | J74: N
A75: ACT-00074 | B75: ACC-10026 | C75: 46077 | D75: status_check | E75: representative_03 | F75: legacy_db | G75: awaiting_review | H75: 46078 | I75: 3 | J75: N
A76: ACT-00075 | B76: ACC-10026 | C76: 46078 | D76: sms_reminder | E76: representative_38 | F76: spreadsheet | G76: sent_to_specialist | I76: 3 | J76: N
A77: ACT-00076 | B77: ACC-10027 | C77: 46054 | D77: escalation | E77: representative_32 | F77: spreadsheet | G77: sent_to_specialist | H77: 46055 | I77: 8 | J77: N
A78: ACT-00077 | B78: ACC-10027 | C78: 46050 | D78: manual_plan_note | E78: representative_43 | F78: email | G78: awaiting_review | H78: 46057 | I78: 8 | J78: N
A79: ACT-00078 | B79: ACC-10028 | C79: 46060 | D79: sms_reminder | E79: representative_18 | F79: phone | G79: promise_to_pay | H79: 46060 | I79: 3 | J79: N
A80: ACT-00079 | B80: ACC-10028 | C80: 46059 | D80: spreadsheet_reconcile | E80: representative_16 | F80: email | G80: awaiting_review | I80: 6 | J80: Y
A81: ACT-00080 | B81: ACC-10028 | C81: 46064 | D81: manual_plan_note | E81: representative_51 | F81: legacy_db | G81: viewed_status | H81: 46065 | I81: 9 | J81: N
A82: ACT-00081 | B82: ACC-10029 | C82: 46043 | D82: sms_reminder | E82: representative_27 | F82: legacy_db | G82: no_reply | I82: 2 | J82: N
A83: ACT-00082 | B83: ACC-10029 | C83: 46039 | D83: sms_reminder | E83: representative_56 | F83: email | G83: promise_to_pay | H83: 46046 | I83: 3 | J83: N
A84: ACT-00083 | B84: ACC-10029 | C84: 46051 | D84: escalation | E84: representative_40 | F84: phone | G84: left_message | H84: 46051 | I84: 10 | J84: N
A85: ACT-00084 | B85: ACC-10030 | C85: 46061 | D85: spreadsheet_reconcile | E85: representative_03 | F85: legacy_db | G85: awaiting_review | H85: 46064 | I85: 12 | J85: N
A86: ACT-00085 | B86: ACC-10030 | C86: 46062 | D86: escalation | E86: representative_29 | F86: email | G86: promise_to_pay | H86: 46066 | I86: 7 | J86: N
A87: ACT-00086 | B87: ACC-10031 | C87: 46049 | D87: sms_reminder | E87: representative_41 | F87: legacy_db | G87: updated_row | H87: 46055 | I87: 2 | J87: N
A88: ACT-00087 | B88: ACC-10032 | C88: 46067 | D88: status_check | E88: representative_23 | F88: spreadsheet | G88: promise_to_pay | H88: 46068 | I88: 5 | J88: Y
A89: ACT-00088 | B89: ACC-10032 | C89: 46075 | D89: spreadsheet_reconcile | E89: representative_44 | F89: spreadsheet | G89: promise_to_pay | H89: 46075 | I89: 9 | J89: N
A90: ACT-00089 | B90: ACC-10032 | C90: 46075 | D90: escalation | E90: representative_52 | F90: phone | G90: updated_row | H90: 46076 | I90: 9 | J90: N
A91: ACT-00090 | B91: ACC-10032 | C91: 46070 | D91: escalation | E91: representative_20 | F91: email | G91: promise_to_pay | H91: 46074 | I91: 9 | J91: N
A92: ACT-00091 | B92: ACC-10033 | C92: 46061 | D92: escalation | E92: representative_14 | F92: phone | G92: viewed_status | H92: 46062 | I92: 11 | J92: N
A93: ACT-00092 | B93: ACC-10033 | C93: 46071 | D93: sms_reminder | E93: representative_49 | F93: email | G93: promise_to_pay | H93: 46071 | I93: 4 | J93: N
A94: ACT-00093 | B94: ACC-10033 | C94: 46071 | D94: spreadsheet_reconcile | E94: representative_04 | F94: legacy_db | G94: promise_to_pay | H94: 46075 | I94: 8 | J94: N
... A96: ACT-00095 | B96: ACC-10033 | C96: 46080 | D96: email_sent | E96: representative_50 | F96: email | G96: sent_to_specialist | H96: 46080 | I96: 5 | J96: N
A97: ACT-00096 | B97: ACC-10034 | C97: 46032 | D97: sms_reminder | E97: representative_39 | F97: email | G97: left_message | I97: 3 | J97: N
A98: ACT-00097 | B98: ACC-10034 | C98: 46038 | D98: call_attempt | E98: representative_41 | F98: spreadsheet | G98: sent_to_specialist | H98: 46042 | I98: 8 | J98: N
A99: ACT-00098 | B99: ACC-10034 | C99: 46046 | D99: email_sent | E99: representative_39 | F99: phone | G99: no_reply | H99: 46049 | I99: 5 | J99: N
A100: ACT-00099 | B100: ACC-10035 | C100: 46066 | D100: sms_reminder | E100: representative_22 | F100: spreadsheet | G100: updated_row | H100: 46067 | I100: 3 | J100: N
A101: ACT-00100 | B101: ACC-10036 | C101: 46050 | D101: manual_plan_note | E101: representative_49 | F101: phone | G101: promise_to_pay | H101: 46051 | I101: 8 | J101: N
...

Sheet Stakeholder Evidence
A1: Stakeholder | B1: Quote or Observation | C1: Theme | D1: Business Impact | E1: Confidence Level
A2: Amina Rahman (Compliance Liaison) | B2: Customers respond well when they have control and transparency about what they owe. | C2: Customer friction | D2: Transparent balance presentation increases voluntary settlements and lowers inbound support call volume. | E2: High
A3: Daniel Okoye (Finance Business Partner) | B3: Customers call back three times because they do not remember what they were told on the first call. | C3: Customer friction | D3: Repeat inbound calls inflate handling costs and extend the average resolution cycle time. | E3: High
A4: Tracy Field (Systems Administrator) | B4: Some customers will do anything if given the chance to manage this themselves. | C4: Customer friction | D4: Lack of digital self-service tools forces willing payers into high-cost manual agent channels. | E4: High
A5: Kimberley Richards-Stokes (Service Design Lead) | B5: Some customers will never use a portal no matter how good it is, and we need to plan for that. | C5: Customer friction | D5: Channel strategy must preserve assisted support options for digitally excluded or resistant customers. | E5: High
A6: Eleanor Clark (Service Design Lead) | B6: Most customers do not even know they can pay online; they think they have to call. | C6: Customer friction | D6: Low digital channel awareness drives unnecessary telephone queues and inflates operational expenses. | E6: High
A7: Robert Quinn (Process Improvement Lead) | B7: Customers get transferred between departments and have to repeat their entire situation each time. | C7: Customer friction | D7: Inter-departmental handoffs frustrate customers, lowering satisfaction and escalating complaint risk. | E7: High
A8: Diana White (Collections Representative) | B8: We are exposed to complaint risk because customers cannot track what we have told them. | C8: Customer friction | D8: Absence of customer-visible confirmation logs invites payment disputes and ombudsman escalations. | E8: High
A9: Dr Lynda Smith (Operations Analyst) | B9: Customers would pay more readily if they understood exactly what they owe and could see options. | C9: Customer friction | D9: Providing transparent balance breakdowns and flexible installment options accelerates payment velocity. | E9: High
A10: Tracy Field (Compliance Liaison) | B10: If the portal works, it will work because it gives customers control, not because it is fancier. | C10: Customer friction | D10: Customer empowerment and autonomy serve as the primary behavioral drivers for digital debt resolution. | E10: High
A11: Tracy Field (Compliance Liaison) | B11: The portal could work brilliantly for the 40% of customers who want to resolve this themselves. | C11: Customer friction | D11: Diverting 40% of routine cases to self-service unlocks major frontline capacity for complex arrears. | E11: High
A12: Thomas Wright (Operations Manager) | B12: If the portal works, it will work because it gives customers control, not because it is fancier. | C12: Customer friction | D12: Focusing on user autonomy over aesthetic complexity ensures higher self-service adoption. | E12: High
... A127: James Morrison (Quality Assurance Lead) | B127: Our representatives are creative and adaptable; they will find ways to use the portal effectively. | C127: Change resistance or distrust | D127: Staff adaptability offers a strong foundation for successful digital change management. | E127: Medium

Sheet JTBD Analysis
A1: JTBD ID | B1: Actor | C1: Statement | D1: Evidence Link | E1: Portal Relevance | F1: Frequency of Evidence | G1: Business Impact Rank | H1: Portal Relevance Rank | I1: Overall Priority
A2: JTBD-01 | B2: Customer | C2: When I need to resolve an outstanding balance, I want to see exactly what I owe and the options available, so I can choose a manageable way to pay. | D2: Dr Lynda Smith (Operations Analyst): "Customers would pay more readily if they understood exactly what they owe and could see options." | E2: Shows clear balance details and enables customers to set up manageable payment plans directly online. | F2: High | G2: High | H2: High | I2: High
A3: JTBD-02 | B3: Customer | C3: When my case moves between departments, I want my history and previous conversations to follow me, so I do not have to explain my situation again. | D3: Robert Quinn (Process Improvement Lead): "Customers get transferred between departments and have to repeat their entire situation each time." | E3: Maintains a shared history across departments so customers never have to repeat their situation when transferred. | F3: Medium | G3: High | H3: High | I3: High
A4: JTBD-03 | B4: Collections representative | C4: When I pick up a case, I want to see recent contacts and promised callbacks in one reliable place, so I can follow through without duplicating outreach. | D4: Christopher Richards (Collections Representative): "The collections database does not sync with the email tracker, so representatives often re-contact customers who were already promised callbacks." | E4: Syncs customer online actions and payment promises into staff records to prevent duplicate outreach. | F4: Medium | G4: High | H4: Medium | I4: Medium
A5: JTBD-04 | B5: Operations manager | C5: When new cases enter the workflow, I want them routed according to their needs and complexity, so straightforward cases are not delayed behind cases requiring specialist handling. | D5: Priya Nair (Operations Manager): "Simple cases that could be resolved in minutes take days because they get stuck in the wrong queue." | E5: Handles routine payments online, freeing staff queues to focus on complex cases needing specialist help. | F5: High | G5: High | H5: High | I5: High
A6: JTBD-05 | B6: Customer | C6: When I need an update on my account, I want to see a clear record of past conversations, actions, and next steps, so I can check my progress without calling for information I have already been given. | D6: Diana White: "We are exposed to complaint risk because customers cannot track what we have told them." & Daniel Okoye | E6: Provides an account dashboard with payment history and agreed plans so customers can check progress without calling. | F6: High | G6: High | H6: High | I6: High
A7: JTBD-06 | B7: Finance analyst | C7: When forecasting recovery revenue, I want timely, reliable activity data, so I can produce forecasts with confidence. | D7: Daniel Farmer (Finance Analyst): "The finance team cannot forecast recovery revenue because they do not trust the activity data." | E7: Captures accurate transaction and payment records to provide reliable data for financial forecasting. | F7: Low | G7: High | H7: Low | I7: Medium
A8: JTBD-07 | B8: Operations manager | C8: When reviewing a case, I want its audit trail available in one place, so I can demonstrate what happened without reconciling scattered records. | D8: Andrea Hunt (Operations Manager): "The audit trail is scattered across email, spreadsheets, and the legacy database, making compliance reviews a nightmare." | E8: Creates a single, clear record of all account actions and agreements for straightforward compliance audits. | F8: High | G8: High | H8: Medium | I8: High
A9: JTBD-08 | B9: Customer | C9: When I believe my balance is incorrect, I want a clear way to raise and track a dispute, so I can get the issue reviewed before being asked to pay. | D9: Simon Burns (Compliance Liaison): "The portal would be great, but what happens when someone disputes the balance?" | E9: Allows customers to submit disputes, upload documents, and pause collections while issues are reviewed. | F9: Medium | G9: High | H9: High | I9: High
A10: JTBD-09 | B10: Collections representative | C10: When I promise a customer a callback, I want the due date recorded and surfaced to the right person, so the customer is not left waiting and the case keeps moving. | D10: Dr Louis Sinclair (Service Design Lead): "Cases get stuck in 'pending callback' status indefinitely because the callback date is never enforced." | E10: Lets customers book callback times that sync directly to staff schedules to ensure timely follow-ups. | F10: High | G10: High | H10: Medium | I10: Medium
A11: JTBD-10 | B11: Customer service representative | C11: When a customer may be experiencing hardship or vulnerability, I want to assess their circumstances with appropriate discretion, so they receive support that fits their situation rather than an unsuitable automated decision. | D11: Peter Chambers (Customer Service Lead): "We cannot automate the decision about whether a customer is genuinely in hardship or just dodging contact." | E11: Spots signs of financial hardship or vulnerability and immediately routes customers to specialist support. | F11: High | G11: High | H11: High | I11: High
E20: Job | F20: Strategic Role | G20: Why It’s in the Top 3
E21: **JTBD-01** *(Balance & Plan)* | F21: **The Front Door** | G21: Gives the 40% of straightforward customers total transparency and the ability to self-serve immediately.
E22: **JTBD-04** *(Smart Triage)* | F22: **The Operational Core** | G22: Unblocks staff queues by separating simple routine arrears from complex debt.
E23: **JTBD-10** *(Vulnerability Off-Ramp)* | F23: **The Safety Shield** | G23: Ensures regulatory compliance and protects vulnerable debtors by routing them straight to human specialists.

Sheet Task Breakdown
A1: Task Name | B1: Task Count | C1: Total Minutes | D1: Average Minutes | E1: Calculation & Origin
A2: call_attempt | B2: =COUNTIF('Recovery activity tracker'!$D$2:$D$9891, A2) -> 1397 | C2: =SUMIF('Recovery activity tracker'!$D$2:$D$9891, A2, 'Recovery activity tracker'!$I$2:$I$9891) -> 15312 | D2: =IFERROR(C2/B2, 0) -> 10.96063 | E2: Aggregated from Recovery activity tracker: Task Count = COUNTIF(activity_type,"call_attempt"); Total Mins = SUMIF(activity_type,"call_attempt",minutes_spent); Avg = 15,312 / 1,397 = 11.0 mins.
A3: email_sent | B3: =COUNTIF('Recovery activity tracker'!$D$2:$D$9891, A3) -> 1382 | C3: =SUMIF('Recovery activity tracker'!$D$2:$D$9891, A3, 'Recovery activity tracker'!$I$2:$I$9891) -> 7580 | D3: =IFERROR(C3/B3, 0) -> 5.4848046 | E3: Aggregated from Recovery activity tracker: Task Count = COUNTIF(activity_type,"email_sent"); Total Mins = SUMIF(activity_type,"email_sent",minutes_spent); Avg = 7,580 / 1,382 = 5.5 mins.
A4: escalation | B4: =COUNTIF('Recovery activity tracker'!$D$2:$D$9891, A4) -> 1423 | C4: =SUMIF('Recovery activity tracker'!$D$2:$D$9891, A4, 'Recovery activity tracker'!$I$2:$I$9891) -> 12025 | D4: =IFERROR(C4/B4, 0) -> 8.4504568 | E4: Aggregated from Recovery activity tracker: Task Count = COUNTIF(activity_type,"escalation"); Total Mins = SUMIF(activity_type,"escalation",minutes_spent); Avg = 12,025 / 1,423 = 8.5 mins.
A5: manual_plan_note | B5: =COUNTIF('Recovery activity tracker'!$D$2:$D$9891, A5) -> 1405 | C5: =SUMIF('Recovery activity tracker'!$D$2:$D$9891, A5, 'Recovery activity tracker'!$I$2:$I$9891) -> 10554 | D5: =IFERROR(C5/B5, 0) -> 7.5117438 | E5: Aggregated from Recovery activity tracker: Task Count = COUNTIF(activity_type,"manual_plan_note"); Total Mins = SUMIF(activity_type,"manual_plan_note",minutes_spent); Avg = 10,554 / 1,405 = 7.5 mins.
A6: sms_reminder | B6: =COUNTIF('Recovery activity tracker'!$D$2:$D$9891, A6) -> 1425 | C6: =SUMIF('Recovery activity tracker'!$D$2:$D$9891, A6, 'Recovery activity tracker'!$I$2:$I$9891) -> 4285 | D6: =IFERROR(C6/B6, 0) -> 3.0070175 | E6: Aggregated from Recovery activity tracker: Task Count = COUNTIF(activity_type,"sms_reminder"); Total Mins = SUMIF(activity_type,"sms_reminder",minutes_spent); Avg = 4,285 / 1,425 = 3.0 mins.
A7: spreadsheet_reconcile | B7: =COUNTIF('Recovery activity tracker'!$D$2:$D$9891, A7) -> 1458 | C7: =SUMIF('Recovery activity tracker'!$D$2:$D$9891, A7, 'Recovery activity tracker'!$I$2:$I$9891) -> 13123 | D7: =IFERROR(C7/B7, 0) -> 9.0006859 | E7: Aggregated from Recovery activity tracker: Task Count = COUNTIF(activity_type,"spreadsheet_reconcile"); Total Mins = SUMIF(activity_type,"spreadsheet_reconcile",minutes_spent); Avg = 13,123 / 1,458 = 9.0 mins. Baseline source for B-03 and OP-06.
A8: status_check | B8: =COUNTIF('Recovery activity tracker'!$D$2:$D$9891, A8) -> 1400 | C8: =SUMIF('Recovery activity tracker'!$D$2:$D$9891, A8, 'Recovery activity tracker'!$I$2:$I$9891) -> 6347 | D8: =IFERROR(C8/B8, 0) -> 4.5335714 | E8: Aggregated from Recovery activity tracker: Task Count = COUNTIF(activity_type,"status_check"); Total Mins = SUMIF(activity_type,"status_check",minutes_spent); Avg = 6,347 / 1,400 = 4.5 mins. Sourced as balance inquiry baseline for assumption FA-24 and opportunity OP-01 (404 annualized hours saved).
A9: Total / Portfolio Average | B9: =SUM(B2:B8) -> 9890 | C9: =SUM(C2:C8) -> 69226 | D9: =IFERROR(C9/B9, 0) -> 6.9995956 | E9: Portfolio total across all logged recovery records: Count = SUM(B2:B8) (9,890 tasks); Total Mins = SUM(C2:C8) (69,226 mins); Portfolio Weighted Average = 69,226 / 9,890 = 7.0 mins (Assumption FA-16).

Sheet Assumptions
A1: assumption_id | B1: assumption_name | C1: value | D1: unit | E1: source | F1: confidence_level | G1: notes | H1: Calculation & Origin
A2: FA-01 | B2: representative_hourly_cost | C2: 22 | D2: GBP | E2: Finance workbook | F2: High | G2: Blended representative hourly cost | H2: Sourced from Finance workbook and HR payroll models; represents the standard fully loaded representative wage (£22/hr) including employment taxes and facility overhead.
A3: FA-02 | B3: working_days_per_month | C3: 21 | D3: days | E3: Finance workbook | F3: High | G3: Used for admin calculations | H3: Sourced from Finance operational calendar; calculated as standard 252 annual working days divided by 12 months = 21 average working days per month.
A4: FA-03 | B4: straightforward_case_share | C4: 0.38 | D4: ratio | E4: Operations estimate | F4: Medium | G4: Suitable for rules-driven self-service | H4: Sourced from Operations leadership estimate and stakeholder interviews (SN-082, SN-099); represents the estimated 38% proportion of delinquent cases eligible for automated/self-service deflection.
A5: FA-04 | B5: avg_straightforward_case_minutes | C5: 18 | D5: minutes | E5: Operations leadership | F5: Medium | G5: Current case handling time | H5: Sourced from Operations leadership time-and-motion study; represents the current baseline handling duration (18 mins) for manual representative handling of routine arrears inquiries.
A6: FA-05 | B6: target_straightforward_case_minutes | C6: 10 | D6: minutes | E6: Operations target | F6: Medium | G6: Target after automation support | H6: Target set by Operations leadership; assumes digital self-service balance viewing and automated routing reduce representative handling time by 8 minutes down to 10 minutes per case.
A7: FA-06 | B7: missed_follow_up_rate | C7: 0.14 | D7: ratio | E7: Activity tracker analysis | F7: Medium | G7: Indicative rate of missed or delayed follow-up | H7: Derived from Recovery activity tracker log analysis (~14.8% unassigned follow-up dates) and operational benchmarks; reflects estimated rate of missed or delayed follow-ups.
A8: FA-07 | B8: recovery_uplift_for_plan_selection | C8: 0.04 | D8: ratio | E8: Finance estimate | F8: Low | G8: Test in sensitivity analysis | H8: Modeled in Finance sensitivity analysis; represents an estimated 4.0% recovery rate uplift on delinquent balances when debtors select structured self-serve payment plans.
A9: FA-08 | B9: recovery_uplift_for_promise_capture | C9: 0.025 | D9: ratio | E9: Finance estimate | F9: Low | G9: Scenario based | H9: Modeled in Finance scenario analysis; represents an estimated 2.5% recovery rate uplift achieved via immediate digital capture and automated confirmation of promises to pay.
A10: FA-09 | B10: monthly_recovery_baseline | C10: 8000000 | D10: GBP | E10: Finance workbook | F10: Medium | G10: Baseline monthly recoveries | H10: Sourced directly from Finance monthly management accounts; reflects baseline gross collections of £8.0M per month (£96M annualized) across delinquent debt operations.
A11: FA-10 | B11: implementation_cost_low_complexity | C11: 45000 | D11: GBP | E11: Product delivery estimate | F11: Medium | G11: Starter figure | H11: Sourced from Product delivery engineering estimates; standard capex cost (£45,000) for low-complexity portal modules (e.g., balance views, reminder dispatch).
A12: FA-11 | B12: implementation_cost_medium_complexity | C12: 85000 | D12: GBP | E12: Product delivery estimate | F12: Medium | G12: Starter figure | H12: Sourced from Product delivery engineering estimates; standard capex cost (£85,000) for medium-complexity integrations (e.g., plan selection engines, routing logic).
A13: FA-12 | B13: total_delinquent_balance | C13: 26559358 | D13: GBP | E13: Delinquent accounts | F13: High | G13: Total portfolio delinquent balance (£3.05M overdue; £940 avg overdue) | H13: Calculated as =SUM(DelinquentAccounts[total_balance]) across all 3,246 customer records in Delinquent accounts tab (£26,559,358.36 total delinquent balance).
... A24: FA-23 | B24: revenue_straightforward_case_share | C24: 0.38 | D24: ratio | E24: Operations estimate | F24: Medium | G24: Straightforward case share applied to revenue calculations | H24: Sourced from FA-03 (38% straightforward case share); applied as eligible case proportion to model revenue uplifts for digital promise capture (OP-03) and payment-plan selection (OP-04).
A25: FA-24 | B25: balance_inquiry_annual_hours_saved | C25: =IFERROR(__xludf.DUMMYFUNCTION("ROUND('Task Breakdown'!C8/60/COUNTUNIQUE('Recovery activity tracker'!$C$2:$C$9891)*$C$3*12, 0)"),404.0) -> 404 | D25: hours | E25: Recovery activity tracker & Task Breakdown | F25: High | G25: Annual representative hours spent on routine balance inquiries (status checks) | H25: Derived from Recovery activity tracker status_check volume (1,400 activities, 6,347 mins across 66 tracking days; Task Breakdown row 8). Annualized as: 6,347 mins / 60 / 66 days * 21 days/mo (FA-02) * 12 mos = 404 annual hours saved for OP-01, replacing prior straightforward case assumption.

Sheet Baseline metrics
A1: metric_id | B1: metric_name | C1: current_value | D1: unit | E1: source | F1: confidence_level | G1: notes | H1: Calculation & Origin
A2: B-01 | B2: total_delinquent_account_volume | C2: =COUNTA('Delinquent accounts'!A2:A3247) -> 3246 | D2: accounts | E2: Delinquent accounts extract | F2: High | G2: Total active delinquent accounts identified from the delinquent accounts extract (ACC-10001 to ACC-13246) | H2: Calculated as =COUNTA(DelinquentAccounts[account_id]) across the Delinquent accounts tab (ACC-10001 through ACC-13246), totaling 3,246 unique active delinquent accounts.
A3: B-02 | B3: likely_straightforward_case_volume | C3: =ROUND(C2*Assumptions!C4, 0) -> 1233 | D3: cases/month | E3: Delinquent accounts & Assumptions (FA-03) | F3: Medium | G3: Estimated monthly straightforward cases based on 38% straightforward case share (FA-03) applied to delinquent accounts | H3: Calculated as =ROUND(B-01 * FA-03) (3,246 delinquent accounts * 38% straightforward case share = 1,233 monthly cases eligible for self-service deflection).
A4: B-03 | B4: admin_hours_spent_on_manual_work | C4: =IFERROR(__xludf.DUMMYFUNCTION("ROUND(SUMIF('Recovery activity tracker'!D:D, ""spreadsheet_reconcile"", 'Recovery activity tracker'!I:I) / 60 / COUNTUNIQUE('Recovery activity tracker'!C2:C9891), 2)"),3.31) -> 3.31 | D4: hours/day | E4: Recovery activity tracker & Assumptions (FA-02) | F4: Medium | G4: Daily representative hours lost to spreadsheet reconciliation (~218.7 hrs total across 66 tracking days) | H4: Calculated from Recovery activity tracker: 13,123 total minutes spent on 'spreadsheet_reconcile' (218.72 hours) divided across 66 tracking days = 3.31 representative hours per working day.
A5: B-04 | B5: missed_follow_up_rate | C5: =Assumptions!C7 -> 0.14 | D5: ratio | E5: Activity tracker analysis (FA-06) | F5: Medium | G5: Indicative baseline rate of missed or delayed follow-ups (FA-06; 14.8% unassigned follow-up dates in activity tracker) | H5: Sourced directly from Assumption FA-06; baseline operational benchmark of unassigned or delayed follow-up schedules identified in activity tracking logs (~14.0%).
A6: B-05 | B6: current_handling_effort_per_straightforward_case | C6: =Assumptions!C5 -> 18 | D6: minutes/case | E6: Operations leadership (FA-04) | F6: Medium | G6: Baseline handling time per straightforward case prior to automation (FA-04) | H6: Sourced directly from Assumption FA-04; operations leadership baseline time-and-motion figure for end-to-end handling of routine arrears inquiries (18 mins/case).
A7: B-06 | B7: monthly_straightforward_case_handling_effort_hours | C7: =ROUND((C3*C6)/60, 1) -> 369.9 | D7: hours/month | E7: Calculated from B-02 and B-05 | F7: Medium | G7: Total monthly staff handling effort devoted to straightforward delinquent cases (1,233 cases * 18 mins / 60) | H7: Calculated as =(B-02 * B-05) / 60; (1,233 straightforward monthly cases * 18 minutes handling time) / 60 minutes = 369.9 representative handling hours per month.
A8: B-07 | B8: monthly_admin_hours_lost_to_reconciliation | C8: =ROUND(C4*Assumptions!C3, 1) -> 69.5 | D8: hours/month | E8: Calculated from B-03 & Assumptions (FA-02) | F8: Medium | G8: Monthly administrative hours lost to manual reconciliation across 21 working days per month (FA-02) | H8: Calculated as =B-03 * FA-02; 3.31 daily admin reconciliation hours * 21 working days per month (FA-02) = 69.51 monthly representative hours lost to reconciliation.
A9: B-08 | B9: total_monthly_manual_effort_hours | C9: =ROUND(C7+C8, 1) -> 439.4 | D9: hours/month | E9: Calculated from B-06 and B-07 | F9: Medium | G9: Combined baseline monthly operational effort from handling straightforward cases and manual reconciliation | H9: Calculated as =B-06 + B-07; 369.9 case handling hours + 69.5 manual reconciliation hours = 439.4 total monthly hours of manual operational effort targeted for automation.

Sheet Opportunities
A1: opportunity_id | B1: opportunity_name | C1: description | D1: implementation_cost | E1: annual_hours_saved | F1: annual_cost_saved | G1: annual_revenue_uplift | H1: soft_benefit_note | I1: confidence_level | J1: priority_rank | K1: Calculation & Origin
A2: OP-01 | B2: self-serve balance and arrears view | C2: Enables customers to view current balances, arrears breakdown, and statement history online, deflecting routine inbound queries. | D2: =Assumptions!$C$11 -> 45000 | E2: =Assumptions!$C$25 -> 404 | F2: =E2*Assumptions!$C$2 -> 8888 | G2: 0 | H2: Empowers customers with transparent balance information, reducing call anxiety and inbound dispute volume. | I2: High | J2: 3 | K2: Implementation cost from FA-10 (£45k); Hours saved (404 hrs/yr) = (6,347 mins / 60 / 66 tracking days) * 252 working days/yr = 403.9 ≈ 404 hrs/yr (annualized from 1,400 status checks under FA-24); Cost saved = 404 hrs * £22/hr (FA-01) = £8,888. Lineage from notes SN-001, SN-065, SN-082.
A3: OP-02 | B3: contact detail confirmation or update request | C3: Allows customers to confirm and update their contact details online, preventing lost outreach and mail returns. | D3: =Assumptions!$C$11 -> 45000 | E3: 240 | F3: =E3*Assumptions!$C$2 -> 5280 | G3: 0 | H3: Maintains high digital contactability (99.7%) and reduces regulatory risk from outdated customer records. | I3: High | J3: 5 | K3: Implementation cost from FA-10 (£45k); Hours saved (240 hrs/yr) = 20 hrs/mo * 12 mos (~0.95 hrs/day across 252 working days, FA-21) avoiding manual address/phone verification; Cost saved = 240 hrs * £22/hr (FA-01) = £5,280. Lineage from contactability data (FA-14: 99.7%) and note SN-088.
A4: OP-03 | B4: digital promise-to-pay capture | C4: Captures digital payment promises and scheduled payment dates online without requiring live agent intervention. | D4: =Assumptions!$C$11 -> 45000 | E4: 360 | F4: =E4*Assumptions!$C$2 -> 7920 | G4: =Assumptions!$C$9*Assumptions!$C$10*12*Assumptions!$C$24 -> 912000 | H4: Secures prompt customer payment commitments and establishes clear behavioral accountability early in arrears. | I4: Medium | J4: 2 | K4: Implementation cost from FA-10 (£45k); Hours saved (360 hrs/yr) = 30 hrs/mo * 12 mos (~1.43 hrs/day across 252 working days) by deflecting routine payment promise calls; Cost saved = 360 hrs * £22/hr (FA-01) = £7,920; Revenue uplift = £8.0M baseline * 12 mos * 2.5% promise capture uplift * 38% straightforward case share (FA-08, FA-09, FA-23) = £912,000. Lineage: SN-112, SN-126.
A5: OP-04 | B5: eligible payment-plan selection | C5: Presents eligible self-service installment plans and payment schedules tailored to customer arrears balance. | D5: =Assumptions!$C$12 -> 85000 | E5: 986 | F5: =E5*Assumptions!$C$2 -> 21692 | G5: =Assumptions!$C$8*Assumptions!$C$10*12*Assumptions!$C$24 -> 1459200 | H5: Drives sustainable debt rehabilitation through manageable terms while preserving agent capacity for complex cases. | I5: Medium | J5: 1 | K5: Implementation cost from FA-11 (£85k); Hours saved (986 hrs/yr) = 1,233 straightforward cases/mo (B-02) * 8 mins saved/case (18 min baseline FA-04 - 10 min target FA-05) * 50% portal self-service adoption * 12 mos / 60 = 986.4 ≈ 986 hrs/yr; Cost saved = 986 hrs * £22/hr (FA-01) = £21,692; Revenue uplift = £8.0M baseline * 12 mos * 4.0% plan selection uplift * 38% straightforward case share (FA-07, FA-09, FA-23) = £1,459,200. Lineage: SN-001, SN-065.
A6: OP-05 | B6: rules-based routing to representatives | C6: Triages cases using predefined rules to direct routine accounts to self-service and route complex or vulnerable debt to specialists. | D6: =Assumptions!$C$12 -> 85000 | E6: 650 | F6: =E6*Assumptions!$C$2 -> 14300 | G6: 0 | H6: Unblocks frontline queues, accelerates straightforward resolution, and protects vulnerable debtors with specialist care. | I6: High | J6: 4 | K6: Implementation cost from FA-11 (£85k); Hours saved (650 hrs/yr) = ~54.2 hrs/mo (~2.58 hrs/day across 252 working days) from automated queue triage and deflection of straightforward cases (FA-03); Cost saved = 650 hrs * £22/hr (FA-01) = £14,300. Lineage from queue friction notes SN-003, SN-029, SN-039, SN-057, SN-079, SN-100.
A7: OP-06 | B7: portal interaction history for representatives | C7: Provides representatives with a unified log of customer portal actions, payment agreements, and communication history. | D7: =Assumptions!$C$11 -> 45000 | E7: ='Baseline metrics'!$C$8*12 -> 834 | F7: =E7*Assumptions!$C$2 -> 18348 | G7: 0 | H7: Eliminates monthly manual spreadsheet reconciliation, prevents duplicate outreach, and provides a clear audit trail. | I7: High | J7: 7 | K7: Implementation cost from FA-10 (£45k); Hours saved (834 hrs/yr) = 69.5 hrs/mo * 12 mos (from 3.31 hrs/day * 21 days/mo, B-03, B-07; eliminates 13,123 mins of reconciliation across 66 tracking days); Cost saved = 834 hrs * £22/hr (FA-01) = £18,348. Lineage: SN-008, SN-011, SN-025, SN-038, SN-123.
A8: OP-07 | B8: automated follow-up reminders | C8: Dispatches automated multi-channel SMS and email reminders for upcoming payment due dates, callbacks, and broken promises. | D8: =Assumptions!$C$11 -> 45000 | E8: 420 | F8: =E8*Assumptions!$C$2 -> 9240 | G8: 0 | H8: Directly addresses the 14% missed follow-up rate, prevents shift handoff drops, and improves promise-kept rates. | I8: Medium | J8: 6 | K8: Implementation cost from FA-10 (£45k); Hours saved (420 hrs/yr) = 35 hrs/mo * 12 mos (~1.67 hrs/day across 252 working days) from automating SMS/email notification workflows; Cost saved = 420 hrs * £22/hr (FA-01) = £9,240. Lineage: resolves 14% missed follow-up rate (FA-06, B-04) and 20% shift handoff loss (FA-20, SN-040, SN-105).

Sheet Calculations
A1: Opportunity ID | B1: Opportunity Name | C1: Implementation Cost | D1: Annual Cost Saved | E1: Annual Revenue Uplift | F1: Annual Total Benefit | G1: Net Benefit | H1: ROI Percentage | I1: Payback Months | J1: Calculation Formula
A2: =Opportunities!A2 -> OP-01 | B2: =Opportunities!B2 -> self-serve balance and arrears view | C2: =Opportunities!D2 -> 45000 | D2: =Opportunities!F2 -> 8888 | E2: =Opportunities!G2 -> 0 | F2: =D2+E2 -> 8888 | G2: =F2-C2 -> -36112 | H2: =IF(C2>0, G2/C2, 0) -> -0.80248889 | I2: =IF(F2>0, C2/(F2/12), "N/A") -> 60.756076 | J2: Total Benefit = Cost Saved + Revenue Uplift; Net Benefit = Total Benefit - Implementation Cost; ROI = Net Benefit / Implementation Cost; Payback = Implementation Cost / (Total Benefit / 12)
A3: =Opportunities!A3 -> OP-02 | B3: =Opportunities!B3 -> contact detail confirmation or update request | C3: =Opportunities!D3 -> 45000 | D3: =Opportunities!F3 -> 5280 | E3: =Opportunities!G3 -> 0 | F3: =D3+E3 -> 5280 | G3: =F3-C3 -> -39720 | H3: =IF(C3>0, G3/C3, 0) -> -0.88266667 | I3: =IF(F3>0, C3/(F3/12), "N/A") -> 102.27273 | J3: Total Benefit = Cost Saved + Revenue Uplift; Net Benefit = Total Benefit - Implementation Cost; ROI = Net Benefit / Implementation Cost; Payback = Implementation Cost / (Total Benefit / 12)
A4: =Opportunities!A4 -> OP-03 | B4: =Opportunities!B4 -> digital promise-to-pay capture | C4: =Opportunities!D4 -> 45000 | D4: =Opportunities!F4 -> 7920 | E4: =Opportunities!G4 -> 912000 | F4: =D4+E4 -> 919920 | G4: =F4-C4 -> 874920 | H4: =IF(C4>0, G4/C4, 0) -> 19.442667 | I4: =IF(F4>0, C4/(F4/12), "N/A") -> 0.58700757 | J4: Total Benefit = Cost Saved + Revenue Uplift; Net Benefit = Total Benefit - Implementation Cost; ROI = Net Benefit / Implementation Cost; Payback = Implementation Cost / (Total Benefit / 12)
A5: =Opportunities!A5 -> OP-04 | B5: =Opportunities!B5 -> eligible payment-plan selection | C5: =Opportunities!D5 -> 85000 | D5: =Opportunities!F5 -> 21692 | E5: =Opportunities!G5 -> 1459200 | F5: =D5+E5 -> 1480892 | G5: =F5-C5 -> 1395892 | H5: =IF(C5>0, G5/C5, 0) -> 16.422259 | I5: =IF(F5>0, C5/(F5/12), "N/A") -> 0.68877406 | J5: Total Benefit = Cost Saved + Revenue Uplift; Net Benefit = Total Benefit - Implementation Cost; ROI = Net Benefit / Implementation Cost; Payback = Implementation Cost / (Total Benefit / 12)
A6: =Opportunities!A6 -> OP-05 | B6: =Opportunities!B6 -> rules-based routing to representatives | C6: =Opportunities!D6 -> 85000 | D6: =Opportunities!F6 -> 14300 | E6: =Opportunities!G6 -> 0 | F6: =D6+E6 -> 14300 | G6: =F6-C6 -> -70700 | H6: =IF(C6>0, G6/C6, 0) -> -0.83176471 | I6: =IF(F6>0, C6/(F6/12), "N/A") -> 71.328671 | J6: Total Benefit = Cost Saved + Revenue Uplift; Net Benefit = Total Benefit - Implementation Cost; ROI = Net Benefit / Implementation Cost; Payback = Implementation Cost / (Total Benefit / 12)
A7: =Opportunities!A7 -> OP-06 | B7: =Opportunities!B7 -> portal interaction history for representatives | C7: =Opportunities!D7 -> 45000 | D7: =Opportunities!F7 -> 18348 | E7: =Opportunities!G7 -> 0 | F7: =D7+E7 -> 18348 | G7: =F7-C7 -> -26652 | H7: =IF(C7>0, G7/C7, 0) -> -0.59226667 | I7: =IF(F7>0, C7/(F7/12), "N/A") -> 29.431001 | J7: Total Benefit = Cost Saved + Revenue Uplift; Net Benefit = Total Benefit - Implementation Cost; ROI = Net Benefit / Implementation Cost; Payback = Implementation Cost / (Total Benefit / 12)
A8: =Opportunities!A8 -> OP-07 | B8: =Opportunities!B8 -> automated follow-up reminders | C8: =Opportunities!D8 -> 45000 | D8: =Opportunities!F8 -> 9240 | E8: =Opportunities!G8 -> 0 | F8: =D8+E8 -> 9240 | G8: =F8-C8 -> -35760 | H8: =IF(C8>0, G8/C8, 0) -> -0.79466667 | I8: =IF(F8>0, C8/(F8/12), "N/A") -> 58.441558 | J8: Total Benefit = Cost Saved + Revenue Uplift; Net Benefit = Total Benefit - Implementation Cost; ROI = Net Benefit / Implementation Cost; Payback = Implementation Cost / (Total Benefit / 12)
A9: Portfolio Total | B9: All Opportunities Rollup | C9: =SUM(C2:C8) -> 395000 | D9: =SUM(D2:D8) -> 85668 | E9: =SUM(E2:E8) -> 2371200 | F9: =SUM(F2:F8) -> 2456868 | G9: =SUM(G2:G8) -> 2061868 | H9: =IF(C9>0, G9/C9, 0) -> 5.219919 | I9: =IF(F9>0, C9/(F9/12), "N/A") -> 1.9292856 | J9: Portfolio totals and aggregate weighted metrics (Net Benefit = Total Benefit - Total Cost; Overall ROI = Net Benefit / Total Cost; Portfolio Payback = Total Cost / (Total Benefit / 12))

Sheet ROI Summary
A1: opportunity_id | B1: opportunity_name | C1: total_benefit | D1: net_benefit | E1: roi_percent | F1: payback_months | G1: effort_score | H1: confidence_level | I1: recommendation_note
A2: OP-01 | B2: =Calculations!B2 -> self-serve balance and arrears view | C2: =Calculations!F2 -> 8888 | D2: =Calculations!G2 -> -36112 | E2: =Calculations!H2 -> -0.80248889 | F2: =Calculations!I2 -> 60.756076 | G2: Low | H2: =Opportunities!I2 -> High | I2: Core Week 2 Scope: Foundational self-service balance & arrears view (JTBD-01); transparent debt visibility drives customer engagement.
A3: OP-02 | B3: =Calculations!B3 -> contact detail confirmation or update request | C3: =Calculations!F3 -> 5280 | D3: =Calculations!G3 -> -39720 | E3: =Calculations!H3 -> -0.88266667 | F3: =Calculations!I3 -> 102.27273 | G3: Low | H3: =Opportunities!I3 -> High | I3: Secondary / Fast-follow: Contact detail updates maintain 99.7% contactability and eliminate mail returns; low effort bundle for Week 2.
A4: OP-03 | B4: =Calculations!B4 -> digital promise-to-pay capture | C4: =Calculations!F4 -> 919920 | D4: =Calculations!G4 -> 874920 | E4: =Calculations!H4 -> 19.442667 | F4: =Calculations!I4 -> 0.58700757 | G4: Low | H4: =Opportunities!I4 -> Medium | I4: Essential Week 2 Scope: Top ROI quick win (£912k revenue uplift, 0.6 mo payback); captures digital payment promises early in delinquency.
A5: OP-04 | B5: =Calculations!B5 -> eligible payment-plan selection | C5: =Calculations!F5 -> 1480892 | D5: =Calculations!G5 -> 1395892 | E5: =Calculations!H5 -> 16.422259 | F5: =Calculations!I5 -> 0.68877406 | G5: Medium | H5: =Opportunities!I5 -> Medium | I5: Primary Week 2 Priority: Highest monetary return (£1.46M revenue uplift, £1.40M net benefit); self-service installment plan selection.
A6: OP-05 | B6: =Calculations!B6 -> rules-based routing to representatives | C6: =Calculations!F6 -> 14300 | D6: =Calculations!G6 -> -70700 | E6: =Calculations!H6 -> -0.83176471 | F6: =Calculations!I6 -> 71.328671 | G6: Medium | H6: =Opportunities!I6 -> High | I6: Essential Week 2 Scope: Operational backbone & triage safety shield (JTBD-04/10); routes routine cases to portal and vulnerable debt to specialists.
A7: OP-06 | B7: =Calculations!B7 -> portal interaction history for representatives | C7: =Calculations!F7 -> 18348 | D7: =Calculations!G7 -> -26652 | E7: =Calculations!H7 -> -0.59226667 | F7: =Calculations!I7 -> 29.431001 | G7: Low | H7: =Opportunities!I7 -> High | I7: Deferred Post-Week 2: Unifies staff portal interaction history (834 hrs saved); deploy after core debtor-facing portal features.
A8: OP-07 | B8: =Calculations!B8 -> automated follow-up reminders | C8: =Calculations!F8 -> 9240 | D8: =Calculations!G8 -> -35760 | E8: =Calculations!H8 -> -0.79466667 | F8: =Calculations!I8 -> 58.441558 | G8: Low | H8: =Opportunities!I8 -> Medium | I8: Sprint 2 Follow-on: Automated reminders targeting 14% missed follow-up rate; activate once digital promise workflows are live.
A9: Portfolio Total | B9: =Calculations!B9 -> All Opportunities Rollup | C9: =Calculations!F9 -> 2456868 | D9: =Calculations!G9 -> 2061868 | E9: =Calculations!H9 -> 5.219919 | F9: =Calculations!I9 -> 1.9292856 | G9: Blended (Total £395k) | H9: High / Medium | I9: Portfolio Recommendation: Prioritize OP-01, OP-03, OP-04, and OP-05 for Week 2 core scope to capture 97%+ of portfolio financial return.
A11: CONSERVATIVE SCENARIO (30% Lower Revenue Uplift, 20% Lower Operational Time Savings)
A12: opportunity_id | B12: opportunity_name | C12: total_benefit | D12: net_benefit | E12: roi_percent | F12: payback_months | G12: effort_score | H12: confidence_level | I12: scenario_note
A13: OP-01 | B13: =B2 -> self-serve balance and arrears view | C13: =Calculations!D2*0.8+Calculations!E2*0.7 -> 7110.4 | D13: =C13-Calculations!C2 -> -37889.6 | E13: =IF(Calculations!C2>0, D13/Calculations!C2, 0) -> -0.84199111 | F13: =IF(C13>0, Calculations!C2/(C13/12), "N/A") -> 75.945095 | G13: =G2 -> Low | H13: =H2 -> High | I13: Deflection volume drops 20%; annual savings reduce to £7.1k, extending payback to 76.0 months.
A14: OP-02 | B14: =B3 -> contact detail confirmation or update request | C14: =Calculations!D3*0.8+Calculations!E3*0.7 -> 4224 | D14: =C14-Calculations!C3 -> -40776 | E14: =IF(Calculations!C3>0, D14/Calculations!C3, 0) -> -0.90613333 | F14: =IF(C14>0, Calculations!C3/(C14/12), "N/A") -> 127.84091 | G14: =G3 -> Low | H14: =H3 -> High | I14: Customer self-service adoption drops 20%; annual savings reduce to £4.2k, extending payback to 127.8 months.
A15: OP-03 | B15: =B4 -> digital promise-to-pay capture | C15: =Calculations!D4*0.8+Calculations!E4*0.7 -> 644736 | D15: =C15-Calculations!C4 -> 599736 | E15: =IF(Calculations!C4>0, D15/Calculations!C4, 0) -> 13.327467 | F15: =IF(C15>0, Calculations!C4/(C15/12), "N/A") -> 0.83755211 | G15: =G4 -> Low | H15: =H4 -> Medium | I15: 30% lower promise recovery yield; still delivers £644.7k total benefit, £599.7k net benefit, and 0.8 mo payback.
A16: OP-04 | B16: =B5 -> eligible payment-plan selection | C16: =Calculations!D5*0.8+Calculations!E5*0.7 -> 1038793.6 | D16: =C16-Calculations!C5 -> 953793.6 | E16: =IF(Calculations!C5>0, D16/Calculations!C5, 0) -> 11.221101 | F16: =IF(C16>0, Calculations!C5/(C16/12), "N/A") -> 0.98190824 | G16: =G5 -> Medium | H16: =H5 -> Medium | I16: 30% lower payment plan recovery yield; still produces £1.04M total benefit, £953.8k net benefit, and 1.0 mo payback.
A17: OP-05 | B17: =B6 -> rules-based routing to representatives | C17: =Calculations!D6*0.8+Calculations!E6*0.7 -> 11440 | D17: =C17-Calculations!C6 -> -73560 | E17: =IF(Calculations!C6>0, D17/Calculations!C6, 0) -> -0.86541176 | F17: =IF(C17>0, Calculations!C6/(C17/12), "N/A") -> 89.160839 | G17: =G6 -> Medium | H17: =H6 -> High | I17: Routine triage deflection drops 20%; annual savings reduce to £11.4k, extending payback to 89.2 months.
A18: OP-06 | B18: =B7 -> portal interaction history for representatives | C18: =Calculations!D7*0.8+Calculations!E7*0.7 -> 14678.4 | D18: =C18-Calculations!C7 -> -30321.6 | E18: =IF(Calculations!C7>0, D18/Calculations!C7, 0) -> -0.67381333 | F18: =IF(C18>0, Calculations!C7/(C18/12), "N/A") -> 36.788751 | G18: =G7 -> Low | H18: =H7 -> High | I18: Reconciliation inquiry savings drop 20%; annual savings reduce to £14.7k, extending payback to 36.8 months.
A19: OP-07 | B19: =B8 -> automated follow-up reminders | C19: =Calculations!D8*0.8+Calculations!E8*0.7 -> 7392 | D19: =C19-Calculations!C8 -> -37608 | E19: =IF(Calculations!C8>0, D19/Calculations!C8, 0) -> -0.83573333 | F19: =IF(C19>0, Calculations!C8/(C19/12), "N/A") -> 73.051948 | G19: =G8 -> Low | H19: =H8 -> Medium | I19: Follow-up reminder efficiency drops 20%; annual savings reduce to £7.4k, extending payback to 73.1 months.
A20: Portfolio Total | B20: Conservative Case Rollup (-30% Revenue, -20% Cost Savings) | C20: =SUM(C13:C19) -> 1728374.4 | D20: =SUM(D13:D19) -> 1333374.4 | E20: =IF(Calculations!C9>0, D20/Calculations!C9, 0) -> 3.3756314 | F20: =IF(C20>0, Calculations!C9/(C20/12), "N/A") -> 2.7424614 | G20: Blended (Total £395k) | H20: Conservative Stress Test | I20: Stress-tested portfolio remains exceptionally viable with £1.33M net benefit, 337% ROI, and 2.8 mo payback.
A22: OPTIMISTIC SCENARIO (30% Higher Recovery Uplift, 20% Higher Operational Time Savings)
A23: opportunity_id | B23: opportunity_name | C23: total_benefit | D23: net_benefit | E23: roi_percent | F23: payback_months | G23: effort_score | H23: confidence_level | I23: scenario_note
A24: OP-01 | B24: =B2 -> self-serve balance and arrears view | C24: =Calculations!D2*1.2+Calculations!E2*1.3 -> 10665.6 | D24: =C24-Calculations!C2 -> -34334.4 | E24: =IF(Calculations!C2>0, D24/Calculations!C2, 0) -> -0.76298667 | F24: =IF(C24>0, Calculations!C2/(C24/12), "N/A") -> 50.630063 | G24: =G2 -> Low | H24: =H2 -> High | I24: Expanded self-service adoption yields £10.7k annual savings (+20%), accelerating payback to 50.6 months.
A25: OP-02 | B25: =B3 -> contact detail confirmation or update request | C25: =Calculations!D3*1.2+Calculations!E3*1.3 -> 6336 | D25: =C25-Calculations!C3 -> -38664 | E25: =IF(Calculations!C3>0, D25/Calculations!C3, 0) -> -0.8592 | F25: =IF(C25>0, Calculations!C3/(C25/12), "N/A") -> 85.227273 | G25: =G3 -> Low | H25: =H3 -> High | I25: High portal engagement lifts automated contact updates to £6.3k annual savings (+20%), shortening payback to 85.2 months.
A26: OP-03 | B26: =B4 -> digital promise-to-pay capture | C26: =Calculations!D4*1.2+Calculations!E4*1.3 -> 1195104 | D26: =C26-Calculations!C4 -> 1150104 | E26: =IF(Calculations!C4>0, D26/Calculations!C4, 0) -> 25.557867 | F26: =IF(C26>0, Calculations!C4/(C26/12), "N/A") -> 0.45184352 | G26: =G4 -> Low | H26: =H4 -> Medium | I26: 30% higher promise conversion lifts total benefit to £1.20M and net benefit to £1.15M, achieving payback in 0.5 months.
A27: OP-04 | B27: =B5 -> eligible payment-plan selection | C27: =Calculations!D5*1.2+Calculations!E5*1.3 -> 1922990.4 | D27: =C27-Calculations!C5 -> 1837990.4 | E27: =IF(Calculations!C5>0, D27/Calculations!C5, 0) -> 21.623416 | F27: =IF(C27>0, Calculations!C5/(C27/12), "N/A") -> 0.53042386 | G27: =G5 -> Medium | H27: =H5 -> Medium | I27: 30% higher plan adoption drives massive £1.92M total benefit and £1.84M net benefit, achieving payback in 0.5 months.
A28: OP-05 | B28: =B6 -> rules-based routing to representatives | C28: =Calculations!D6*1.2+Calculations!E6*1.3 -> 17160 | D28: =C28-Calculations!C6 -> -67840 | E28: =IF(Calculations!C6>0, D28/Calculations!C6, 0) -> -0.79811765 | F28: =IF(C28>0, Calculations!C6/(C28/12), "N/A") -> 59.440559 | G28: =G6 -> Medium | H28: =H6 -> High | I28: Enhanced automated triage deflects more routine queries, generating £17.2k annual savings and 59.4 month payback.
A29: OP-06 | B29: =B7 -> portal interaction history for representatives | C29: =Calculations!D7*1.2+Calculations!E7*1.3 -> 22017.6 | D29: =C29-Calculations!C7 -> -22982.4 | E29: =IF(Calculations!C7>0, D29/Calculations!C7, 0) -> -0.51072 | F29: =IF(C29>0, Calculations!C7/(C29/12), "N/A") -> 24.525834 | G29: =G7 -> Low | H29: =H7 -> High | I29: Broad portal usage maximizes staff interaction lookup savings to £22.0k annually, reducing payback to 24.5 months.
A30: OP-07 | B30: =B8 -> automated follow-up reminders | C30: =Calculations!D8*1.2+Calculations!E8*1.3 -> 11088 | D30: =C30-Calculations!C8 -> -33912 | E30: =IF(Calculations!C8>0, D30/Calculations!C8, 0) -> -0.7536 | F30: =IF(C30>0, Calculations!C8/(C30/12), "N/A") -> 48.701299 | G30: =G8 -> Low | H30: =H8 -> Medium | I30: High reminder engagement lifts staff capacity recovery to £11.1k annual savings, shortening payback to 48.7 months.
A31: Portfolio Total | B31: Optimistic Case Rollup (+30% Revenue, +20% Cost Savings) | C31: =SUM(C24:C30) -> 3185361.6 | D31: =SUM(D24:D30) -> 2790361.6 | E31: =IF(Calculations!C9>0, D31/Calculations!C9, 0) -> 7.0642066 | F31: =IF(C31>0, Calculations!C9/(C31/12), "N/A") -> 1.4880571 | G31: Blended (Total £395k) | H31: Optimistic Upside | I31: Exceptional upside: Accelerated digital adoption delivers £3.19M total benefit, £2.79M net benefit, 707% ROI, and 1.5 mo payback.
